Workbook

Sheet Annual Dashboard
B2: Annual Totals

Sheet Annual Totals
B2: Annual Totals
B3: SUMMARY | C3: JAN | D3: FEB | E3: MAR | F3: APR | G3: MAY | H3: JUN | I3: JUL | J3: AUG | K3: SEP | L3: OCT | M3: NOV | N3: DEC
B4: Income | C4: =INDIRECT(C$3&"!D18") -> 19000 | D4: =INDIRECT(D$3&"!D18") -> 19000 | E4: =INDIRECT(E$3&"!D18") -> 19000 | F4: =INDIRECT(F$3&"!D18") -> 19000 | G4: =INDIRECT(G$3&"!D18") -> 19000 | H4: =INDIRECT(H$3&"!D18") -> 19000 | I4: =INDIRECT(I$3&"!D18") -> 19000 | J4: =INDIRECT(J$3&"!D18") -> 19000 | ... N4: =INDIRECT(N$3&"!D18") -> 19000
B5: Savings | C5: =INDIRECT(C$3&"!D30") -> 0 | D5: =INDIRECT(D$3&"!D30") -> 0 | E5: =INDIRECT(E$3&"!D30") -> 34900 | F5: =INDIRECT(F$3&"!D30") -> 0 | G5: =INDIRECT(G$3&"!D30") -> 0 | H5: =INDIRECT(H$3&"!D30") -> 0 | I5: =INDIRECT(I$3&"!D30") -> 0 | J5: =INDIRECT(J$3&"!D30") -> 1835 | ... N5: =INDIRECT(N$3&"!D30") -> 0
B6: Bills | C6: =INDIRECT(C$3&"!H30") -> 0 | D6: =INDIRECT(D$3&"!H30") -> 0 | E6: =INDIRECT(E$3&"!H30") -> 0 | F6: =INDIRECT(F$3&"!H30") -> 0 | G6: =INDIRECT(G$3&"!H30") -> 0 | H6: =INDIRECT(H$3&"!H30") -> 0 | I6: =INDIRECT(I$3&"!H30") -> 0 | J6: =INDIRECT(J$3&"!H30") -> 0 | ... N6: =INDIRECT(N$3&"!H30") -> 0
B7: Expenses | C7: =INDIRECT(C$3&"!L30") -> 0 | D7: =INDIRECT(D$3&"!L30") -> 0 | E7: =INDIRECT(E$3&"!L30") -> 0 | F7: =INDIRECT(F$3&"!L30") -> 0 | G7: =INDIRECT(G$3&"!L30") -> 0 | H7: =INDIRECT(H$3&"!L30") -> 0 | I7: =INDIRECT(I$3&"!L30") -> 0 | J7: =INDIRECT(J$3&"!L30") -> 0 | ... N7: =INDIRECT(N$3&"!L30") -> 0
B8: Debts | C8: =INDIRECT(C$3&"!P30") -> 0 | D8: =INDIRECT(D$3&"!P30") -> 0 | E8: =INDIRECT(E$3&"!P30") -> 0 | F8: =INDIRECT(F$3&"!P30") -> 0 | G8: =INDIRECT(G$3&"!P30") -> 0 | H8: =INDIRECT(H$3&"!P30") -> 0 | I8: =INDIRECT(I$3&"!P30") -> 0 | J8: =INDIRECT(J$3&"!P30") -> 1700 | ... N8: =INDIRECT(N$3&"!P30") -> 0
B9: BALANCE | C9: =C4-SUM(C5:C8) -> 19000 | D9: =D4-SUM(D5:D8) -> 19000 | E9: =E4-SUM(E5:E8) -> -15900 | F9: =F4-SUM(F5:F8) -> 19000 | G9: =G4-SUM(G5:G8) -> 19000 | H9: =H4-SUM(H5:H8) -> 19000 | I9: =I4-SUM(I5:I8) -> 19000 | J9: =J4-SUM(J5:J8) -> 15465 | ... N9: =N4-SUM(N5:N8) -> 19000
B11: Income
B12: Name | C12: JAN | D12: FEB | E12: MAR | F12: APR | G12: MAY | H12: JUN | I12: JUL | J12: AUG | K12: SEP | L12: OCT | M12: NOV | N12: DEC
B13: Alex Paycheck #1 | C13: =SUMIF(INDIRECT(C$12&"!B10:B17"),$B13,INDIRECT(C$12&"!D10:D17")) -> 0 | D13: =SUMIF(INDIRECT(D$12&"!B10:B17"),$B13,INDIRECT(D$12&"!D10:D17")) -> 0 | E13: =SUMIF(INDIRECT(E$12&"!B10:B17"),$B13,INDIRECT(E$12&"!D10:D17")) -> 0 | F13: =SUMIF(INDIRECT(F$12&"!B10:B17"),$B13,INDIRECT(F$12&"!D10:D17")) -> 0 | G13: =SUMIF(INDIRECT(G$12&"!B10:B17"),$B13,INDIRECT(G$12&"!D10:D17")) -> 0 | H13: =SUMIF(INDIRECT(H$12&"!B10:B17"),$B13,INDIRECT(H$12&"!D10:D17")) -> 0 | I13: =SUMIF(INDIRECT(I$12&"!B10:B17"),$B13,INDIRECT(I$12&"!D10:D17")) -> 0 | J13: =SUMIF(INDIRECT(J$12&"!B10:B17"),$B13,INDIRECT(J$12&"!D10:D17")) -> 0 | ... N13: =SUMIF(INDIRECT(N$12&"!B10:B17"),$B13,INDIRECT(N$12&"!D10:D17")) -> 0
B14: Harper Paycheck #1 | C14: =SUMIF(INDIRECT(C$12&"!B10:B17"),$B14,INDIRECT(C$12&"!D10:D17")) -> 0 | D14: =SUMIF(INDIRECT(D$12&"!B10:B17"),$B14,INDIRECT(D$12&"!D10:D17")) -> 0 | E14: =SUMIF(INDIRECT(E$12&"!B10:B17"),$B14,INDIRECT(E$12&"!D10:D17")) -> 0 | F14: =SUMIF(INDIRECT(F$12&"!B10:B17"),$B14,INDIRECT(F$12&"!D10:D17")) -> 0 | G14: =SUMIF(INDIRECT(G$12&"!B10:B17"),$B14,INDIRECT(G$12&"!D10:D17")) -> 0 | H14: =SUMIF(INDIRECT(H$12&"!B10:B17"),$B14,INDIRECT(H$12&"!D10:D17")) -> 0 | I14: =SUMIF(INDIRECT(I$12&"!B10:B17"),$B14,INDIRECT(I$12&"!D10:D17")) -> 0 | J14: =SUMIF(INDIRECT(J$12&"!B10:B17"),$B14,INDIRECT(J$12&"!D10:D17")) -> 0 | ... N14: =SUMIF(INDIRECT(N$12&"!B10:B17"),$B14,INDIRECT(N$12&"!D10:D17")) -> 0
B15: Freelance Earnings | C15: =SUMIF(INDIRECT(C$12&"!B10:B17"),$B15,INDIRECT(C$12&"!D10:D17")) -> 0 | D15: =SUMIF(INDIRECT(D$12&"!B10:B17"),$B15,INDIRECT(D$12&"!D10:D17")) -> 0 | E15: =SUMIF(INDIRECT(E$12&"!B10:B17"),$B15,INDIRECT(E$12&"!D10:D17")) -> 0 | F15: =SUMIF(INDIRECT(F$12&"!B10:B17"),$B15,INDIRECT(F$12&"!D10:D17")) -> 0 | G15: =SUMIF(INDIRECT(G$12&"!B10:B17"),$B15,INDIRECT(G$12&"!D10:D17")) -> 0 | H15: =SUMIF(INDIRECT(H$12&"!B10:B17"),$B15,INDIRECT(H$12&"!D10:D17")) -> 0 | I15: =SUMIF(INDIRECT(I$12&"!B10:B17"),$B15,INDIRECT(I$12&"!D10:D17")) -> 0 | J15: =SUMIF(INDIRECT(J$12&"!B10:B17"),$B15,INDIRECT(J$12&"!D10:D17")) -> 0 | ... N15: =SUMIF(INDIRECT(N$12&"!B10:B17"),$B15,INDIRECT(N$12&"!D10:D17")) -> 0
B16: Alex Paycheck #2 | C16: =SUMIF(INDIRECT(C$12&"!B10:B17"),$B16,INDIRECT(C$12&"!D10:D17")) -> 0 | D16: =SUMIF(INDIRECT(D$12&"!B10:B17"),$B16,INDIRECT(D$12&"!D10:D17")) -> 0 | E16: =SUMIF(INDIRECT(E$12&"!B10:B17"),$B16,INDIRECT(E$12&"!D10:D17")) -> 0 | F16: =SUMIF(INDIRECT(F$12&"!B10:B17"),$B16,INDIRECT(F$12&"!D10:D17")) -> 0 | G16: =SUMIF(INDIRECT(G$12&"!B10:B17"),$B16,INDIRECT(G$12&"!D10:D17")) -> 0 | H16: =SUMIF(INDIRECT(H$12&"!B10:B17"),$B16,INDIRECT(H$12&"!D10:D17")) -> 0 | I16: =SUMIF(INDIRECT(I$12&"!B10:B17"),$B16,INDIRECT(I$12&"!D10:D17")) -> 0 | J16: =SUMIF(INDIRECT(J$12&"!B10:B17"),$B16,INDIRECT(J$12&"!D10:D17")) -> 0 | ... N16: =SUMIF(INDIRECT(N$12&"!B10:B17"),$B16,INDIRECT(N$12&"!D10:D17")) -> 0
B17: Harper Paycheck #2 | C17: =SUMIF(INDIRECT(C$12&"!B10:B17"),$B17,INDIRECT(C$12&"!D10:D17")) -> 0 | D17: =SUMIF(INDIRECT(D$12&"!B10:B17"),$B17,INDIRECT(D$12&"!D10:D17")) -> 0 | E17: =SUMIF(INDIRECT(E$12&"!B10:B17"),$B17,INDIRECT(E$12&"!D10:D17")) -> 0 | F17: =SUMIF(INDIRECT(F$12&"!B10:B17"),$B17,INDIRECT(F$12&"!D10:D17")) -> 0 | G17: =SUMIF(INDIRECT(G$12&"!B10:B17"),$B17,INDIRECT(G$12&"!D10:D17")) -> 0 | H17: =SUMIF(INDIRECT(H$12&"!B10:B17"),$B17,INDIRECT(H$12&"!D10:D17")) -> 0 | I17: =SUMIF(INDIRECT(I$12&"!B10:B17"),$B17,INDIRECT(I$12&"!D10:D17")) -> 0 | J17: =SUMIF(INDIRECT(J$12&"!B10:B17"),$B17,INDIRECT(J$12&"!D10:D17")) -> 0 | ... N17: =SUMIF(INDIRECT(N$12&"!B10:B17"),$B17,INDIRECT(N$12&"!D10:D17")) -> 0
B18: Investment Interest | C18: =SUMIF(INDIRECT(C$12&"!B10:B17"),$B18,INDIRECT(C$12&"!D10:D17")) -> 0 | D18: =SUMIF(INDIRECT(D$12&"!B10:B17"),$B18,INDIRECT(D$12&"!D10:D17")) -> 0 | E18: =SUMIF(INDIRECT(E$12&"!B10:B17"),$B18,INDIRECT(E$12&"!D10:D17")) -> 0 | F18: =SUMIF(INDIRECT(F$12&"!B10:B17"),$B18,INDIRECT(F$12&"!D10:D17")) -> 0 | G18: =SUMIF(INDIRECT(G$12&"!B10:B17"),$B18,INDIRECT(G$12&"!D10:D17")) -> 0 | H18: =SUMIF(INDIRECT(H$12&"!B10:B17"),$B18,INDIRECT(H$12&"!D10:D17")) -> 0 | I18: =SUMIF(INDIRECT(I$12&"!B10:B17"),$B18,INDIRECT(I$12&"!D10:D17")) -> 0 | J18: =SUMIF(INDIRECT(J$12&"!B10:B17"),$B18,INDIRECT(J$12&"!D10:D17")) -> 0 | ... N18: =SUMIF(INDIRECT(N$12&"!B10:B17"),$B18,INDIRECT(N$12&"!D10:D17")) -> 0
C19: =SUMIF(INDIRECT(C$12&"!B10:B17"),$B19,INDIRECT(C$12&"!D10:D17")) -> 0 | D19: =SUMIF(INDIRECT(D$12&"!B10:B17"),$B19,INDIRECT(D$12&"!D10:D17")) -> 0 | E19: =SUMIF(INDIRECT(E$12&"!B10:B17"),$B19,INDIRECT(E$12&"!D10:D17")) -> 0 | F19: =SUMIF(INDIRECT(F$12&"!B10:B17"),$B19,INDIRECT(F$12&"!D10:D17")) -> 0 | G19: =SUMIF(INDIRECT(G$12&"!B10:B17"),$B19,INDIRECT(G$12&"!D10:D17")) -> 0 | H19: =SUMIF(INDIRECT(H$12&"!B10:B17"),$B19,INDIRECT(H$12&"!D10:D17")) -> 0 | I19: =SUMIF(INDIRECT(I$12&"!B10:B17"),$B19,INDIRECT(I$12&"!D10:D17")) -> 0 | J19: =SUMIF(INDIRECT(J$12&"!B10:B17"),$B19,INDIRECT(J$12&"!D10:D17")) -> 0 | ... N19: =SUMIF(INDIRECT(N$12&"!B10:B17"),$B19,INDIRECT(N$12&"!D10:D17")) -> 0
C20: =SUMIF(INDIRECT(C$12&"!B10:B17"),$B20,INDIRECT(C$12&"!D10:D17")) -> 0 | D20: =SUMIF(INDIRECT(D$12&"!B10:B17"),$B20,INDIRECT(D$12&"!D10:D17")) -> 0 | E20: =SUMIF(INDIRECT(E$12&"!B10:B17"),$B20,INDIRECT(E$12&"!D10:D17")) -> 0 | F20: =SUMIF(INDIRECT(F$12&"!B10:B17"),$B20,INDIRECT(F$12&"!D10:D17")) -> 0 | G20: =SUMIF(INDIRECT(G$12&"!B10:B17"),$B20,INDIRECT(G$12&"!D10:D17")) -> 0 | H20: =SUMIF(INDIRECT(H$12&"!B10:B17"),$B20,INDIRECT(H$12&"!D10:D17")) -> 0 | I20: =SUMIF(INDIRECT(I$12&"!B10:B17"),$B20,INDIRECT(I$12&"!D10:D17")) -> 0 | J20: =SUMIF(INDIRECT(J$12&"!B10:B17"),$B20,INDIRECT(J$12&"!D10:D17")) -> 0 | ... N20: =SUMIF(INDIRECT(N$12&"!B10:B17"),$B20,INDIRECT(N$12&"!D10:D17")) -> 0
B21: Total Income | C21: =SUM(C13:C20) -> 0 | D21: =SUM(D13:D20) -> 0 | E21: =SUM(E13:E20) -> 0 | F21: =SUM(F13:F20) -> 0 | G21: =SUM(G13:G20) -> 0 | H21: =SUM(H13:H20) -> 0 | I21: =SUM(I13:I20) -> 0 | J21: =SUM(J13:J20) -> 0 | ... N21: =SUM(N13:N20) -> 0
B23: Savings
B24: Name | C24: JAN | D24: FEB | E24: MAR | F24: APR | G24: MAY | H24: JUN | I24: JUL | J24: AUG | K24: SEP | L24: OCT | M24: NOV | N24: DEC
B25: Emergency Fund | C25: =SUMIF(INDIRECT(C$24&"!B22:B29"),$B25,INDIRECT(C$24&"!D22:D29")) -> 0 | D25: =SUMIF(INDIRECT(D$24&"!B22:B29"),$B25,INDIRECT(D$24&"!D22:D29")) -> 0 | E25: =SUMIF(INDIRECT(E$24&"!B22:B29"),$B25,INDIRECT(E$24&"!D22:D29")) -> 0 | F25: =SUMIF(INDIRECT(F$24&"!B22:B29"),$B25,INDIRECT(F$24&"!D22:D29")) -> 0 | G25: =SUMIF(INDIRECT(G$24&"!B22:B29"),$B25,INDIRECT(G$24&"!D22:D29")) -> 0 | H25: =SUMIF(INDIRECT(H$24&"!B22:B29"),$B25,INDIRECT(H$24&"!D22:D29")) -> 0 | I25: =SUMIF(INDIRECT(I$24&"!B22:B29"),$B25,INDIRECT(I$24&"!D22:D29")) -> 0 | J25: =SUMIF(INDIRECT(J$24&"!B22:B29"),$B25,INDIRECT(J$24&"!D22:D29")) -> 325 | ... N25: =SUMIF(INDIRECT(N$24&"!B22:B29"),$B25,INDIRECT(N$24&"!D22:D29")) -> 0
B26: Investment Portfolio | C26: =SUMIF(INDIRECT(C$24&"!B22:B29"),$B26,INDIRECT(C$24&"!D22:D29")) -> 0 | D26: =SUMIF(INDIRECT(D$24&"!B22:B29"),$B26,INDIRECT(D$24&"!D22:D29")) -> 0 | E26: =SUMIF(INDIRECT(E$24&"!B22:B29"),$B26,INDIRECT(E$24&"!D22:D29")) -> 0 | F26: =SUMIF(INDIRECT(F$24&"!B22:B29"),$B26,INDIRECT(F$24&"!D22:D29")) -> 0 | G26: =SUMIF(INDIRECT(G$24&"!B22:B29"),$B26,INDIRECT(G$24&"!D22:D29")) -> 0 | H26: =SUMIF(INDIRECT(H$24&"!B22:B29"),$B26,INDIRECT(H$24&"!D22:D29")) -> 0 | I26: =SUMIF(INDIRECT(I$24&"!B22:B29"),$B26,INDIRECT(I$24&"!D22:D29")) -> 0 | J26: =SUMIF(INDIRECT(J$24&"!B22:B29"),$B26,INDIRECT(J$24&"!D22:D29")) -> 550 | ... N26: =SUMIF(INDIRECT(N$24&"!B22:B29"),$B26,INDIRECT(N$24&"!D22:D29")) -> 0
B27: Vacation Fund | C27: =SUMIF(INDIRECT(C$24&"!B22:B29"),$B27,INDIRECT(C$24&"!D22:D29")) -> 0 | D27: =SUMIF(INDIRECT(D$24&"!B22:B29"),$B27,INDIRECT(D$24&"!D22:D29")) -> 0 | E27: =SUMIF(INDIRECT(E$24&"!B22:B29"),$B27,INDIRECT(E$24&"!D22:D29")) -> 0 | F27: =SUMIF(INDIRECT(F$24&"!B22:B29"),$B27,INDIRECT(F$24&"!D22:D29")) -> 0 | G27: =SUMIF(INDIRECT(G$24&"!B22:B29"),$B27,INDIRECT(G$24&"!D22:D29")) -> 0 | H27: =SUMIF(INDIRECT(H$24&"!B22:B29"),$B27,INDIRECT(H$24&"!D22:D29")) -> 0 | I27: =SUMIF(INDIRECT(I$24&"!B22:B29"),$B27,INDIRECT(I$24&"!D22:D29")) -> 0 | J27: =SUMIF(INDIRECT(J$24&"!B22:B29"),$B27,INDIRECT(J$24&"!D22:D29")) -> 210 | ... N27: =SUMIF(INDIRECT(N$24&"!B22:B29"),$B27,INDIRECT(N$24&"!D22:D29")) -> 0
B28: New Vehicle | C28: =SUMIF(INDIRECT(C$24&"!B22:B29"),$B28,INDIRECT(C$24&"!D22:D29")) -> 0 | D28: =SUMIF(INDIRECT(D$24&"!B22:B29"),$B28,INDIRECT(D$24&"!D22:D29")) -> 0 | E28: =SUMIF(INDIRECT(E$24&"!B22:B29"),$B28,INDIRECT(E$24&"!D22:D29")) -> 0 | F28: =SUMIF(INDIRECT(F$24&"!B22:B29"),$B28,INDIRECT(F$24&"!D22:D29")) -> 0 | G28: =SUMIF(INDIRECT(G$24&"!B22:B29"),$B28,INDIRECT(G$24&"!D22:D29")) -> 0 | H28: =SUMIF(INDIRECT(H$24&"!B22:B29"),$B28,INDIRECT(H$24&"!D22:D29")) -> 0 | I28: =SUMIF(INDIRECT(I$24&"!B22:B29"),$B28,INDIRECT(I$24&"!D22:D29")) -> 0 | J28: =SUMIF(INDIRECT(J$24&"!B22:B29"),$B28,INDIRECT(J$24&"!D22:D29")) -> 550 | ... N28: =SUMIF(INDIRECT(N$24&"!B22:B29"),$B28,INDIRECT(N$24&"!D22:D29")) -> 0
B29: Home Improvement | C29: =SUMIF(INDIRECT(C$24&"!B22:B29"),$B29,INDIRECT(C$24&"!D22:D29")) -> 0 | D29: =SUMIF(INDIRECT(D$24&"!B22:B29"),$B29,INDIRECT(D$24&"!D22:D29")) -> 0 | E29: =SUMIF(INDIRECT(E$24&"!B22:B29"),$B29,INDIRECT(E$24&"!D22:D29")) -> 0 | F29: =SUMIF(INDIRECT(F$24&"!B22:B29"),$B29,INDIRECT(F$24&"!D22:D29")) -> 0 | G29: =SUMIF(INDIRECT(G$24&"!B22:B29"),$B29,INDIRECT(G$24&"!D22:D29")) -> 0 | H29: =SUMIF(INDIRECT(H$24&"!B22:B29"),$B29,INDIRECT(H$24&"!D22:D29")) -> 0 | I29: =SUMIF(INDIRECT(I$24&"!B22:B29"),$B29,INDIRECT(I$24&"!D22:D29")) -> 0 | J29: =SUMIF(INDIRECT(J$24&"!B22:B29"),$B29,INDIRECT(J$24&"!D22:D29")) -> 200 | ... N29: =SUMIF(INDIRECT(N$24&"!B22:B29"),$B29,INDIRECT(N$24&"!D22:D29")) -> 0
C30: =SUMIF(INDIRECT(C$24&"!B22:B29"),$B30,INDIRECT(C$24&"!D22:D29")) -> 0 | D30: =SUMIF(INDIRECT(D$24&"!B22:B29"),$B30,INDIRECT(D$24&"!D22:D29")) -> 0 | E30: =SUMIF(INDIRECT(E$24&"!B22:B29"),$B30,INDIRECT(E$24&"!D22:D29")) -> 0 | F30: =SUMIF(INDIRECT(F$24&"!B22:B29"),$B30,INDIRECT(F$24&"!D22:D29")) -> 0 | G30: =SUMIF(INDIRECT(G$24&"!B22:B29"),$B30,INDIRECT(G$24&"!D22:D29")) -> 0 | H30: =SUMIF(INDIRECT(H$24&"!B22:B29"),$B30,INDIRECT(H$24&"!D22:D29")) -> 0 | I30: =SUMIF(INDIRECT(I$24&"!B22:B29"),$B30,INDIRECT(I$24&"!D22:D29")) -> 0 | J30: =SUMIF(INDIRECT(J$24&"!B22:B29"),$B30,INDIRECT(J$24&"!D22:D29")) -> 0 | ... N30: =SUMIF(INDIRECT(N$24&"!B22:B29"),$B30,INDIRECT(N$24&"!D22:D29")) -> 0
C31: =SUMIF(INDIRECT(C$24&"!B22:B29"),$B31,INDIRECT(C$24&"!D22:D29")) -> 0 | D31: =SUMIF(INDIRECT(D$24&"!B22:B29"),$B31,INDIRECT(D$24&"!D22:D29")) -> 0 | E31: =SUMIF(INDIRECT(E$24&"!B22:B29"),$B31,INDIRECT(E$24&"!D22:D29")) -> 0 | F31: =SUMIF(INDIRECT(F$24&"!B22:B29"),$B31,INDIRECT(F$24&"!D22:D29")) -> 0 | G31: =SUMIF(INDIRECT(G$24&"!B22:B29"),$B31,INDIRECT(G$24&"!D22:D29")) -> 0 | H31: =SUMIF(INDIRECT(H$24&"!B22:B29"),$B31,INDIRECT(H$24&"!D22:D29")) -> 0 | I31: =SUMIF(INDIRECT(I$24&"!B22:B29"),$B31,INDIRECT(I$24&"!D22:D29")) -> 0 | J31: =SUMIF(INDIRECT(J$24&"!B22:B29"),$B31,INDIRECT(J$24&"!D22:D29")) -> 0 | ... N31: =SUMIF(INDIRECT(N$24&"!B22:B29"),$B31,INDIRECT(N$24&"!D22:D29")) -> 0
C32: =SUMIF(INDIRECT(C$24&"!B22:B29"),$B32,INDIRECT(C$24&"!D22:D29")) -> 0 | D32: =SUMIF(INDIRECT(D$24&"!B22:B29"),$B32,INDIRECT(D$24&"!D22:D29")) -> 0 | E32: =SUMIF(INDIRECT(E$24&"!B22:B29"),$B32,INDIRECT(E$24&"!D22:D29")) -> 0 | F32: =SUMIF(INDIRECT(F$24&"!B22:B29"),$B32,INDIRECT(F$24&"!D22:D29")) -> 0 | G32: =SUMIF(INDIRECT(G$24&"!B22:B29"),$B32,INDIRECT(G$24&"!D22:D29")) -> 0 | H32: =SUMIF(INDIRECT(H$24&"!B22:B29"),$B32,INDIRECT(H$24&"!D22:D29")) -> 0 | I32: =SUMIF(INDIRECT(I$24&"!B22:B29"),$B32,INDIRECT(I$24&"!D22:D29")) -> 0 | J32: =SUMIF(INDIRECT(J$24&"!B22:B29"),$B32,INDIRECT(J$24&"!D22:D29")) -> 0 | ... N32: =SUMIF(INDIRECT(N$24&"!B22:B29"),$B32,INDIRECT(N$24&"!D22:D29")) -> 0
B33: Total Savings | C33: =SUM(C25:C32) -> 0 | D33: =SUM(D25:D32) -> 0 | E33: =SUM(E25:E32) -> 0 | F33: =SUM(F25:F32) -> 0 | G33: =SUM(G25:G32) -> 0 | H33: =SUM(H25:H32) -> 0 | I33: =SUM(I25:I32) -> 0 | J33: =SUM(J25:J32) -> 1835 | ... N33: =SUM(N25:N32) -> 0
B35: Bills
B36: Name | C36: JAN | D36: FEB | E36: MAR | F36: APR | G36: MAY | H36: JUN | I36: JUL | J36: AUG | K36: SEP | L36: OCT | M36: NOV | N36: DEC
B37: Electricity | C37: =SUMIF(INDIRECT(C$36&"!F10:F29"),$B37,INDIRECT(C$36&"!H10:H29")) -> 0 | D37: =SUMIF(INDIRECT(D$36&"!F10:F29"),$B37,INDIRECT(D$36&"!H10:H29")) -> 0 | E37: =SUMIF(INDIRECT(E$36&"!F10:F29"),$B37,INDIRECT(E$36&"!H10:H29")) -> 0 | F37: =SUMIF(INDIRECT(F$36&"!F10:F29"),$B37,INDIRECT(F$36&"!H10:H29")) -> 0 | G37: =SUMIF(INDIRECT(G$36&"!F10:F29"),$B37,INDIRECT(G$36&"!H10:H29")) -> 0 | H37: =SUMIF(INDIRECT(H$36&"!F10:F29"),$B37,INDIRECT(H$36&"!H10:H29")) -> 0 | I37: =SUMIF(INDIRECT(I$36&"!F10:F29"),$B37,INDIRECT(I$36&"!H10:H29")) -> 0 | J37: =SUMIF(INDIRECT(J$36&"!F10:F29"),$B37,INDIRECT(J$36&"!H10:H29")) -> 0 | ... N37: =SUMIF(INDIRECT(N$36&"!F10:F29"),$B37,INDIRECT(N$36&"!H10:H29")) -> 0
B38: Water | C38: =SUMIF(INDIRECT(C$36&"!F10:F29"),$B38,INDIRECT(C$36&"!H10:H29")) -> 0 | D38: =SUMIF(INDIRECT(D$36&"!F10:F29"),$B38,INDIRECT(D$36&"!H10:H29")) -> 0 | E38: =SUMIF(INDIRECT(E$36&"!F10:F29"),$B38,INDIRECT(E$36&"!H10:H29")) -> 0 | F38: =SUMIF(INDIRECT(F$36&"!F10:F29"),$B38,INDIRECT(F$36&"!H10:H29")) -> 0 | G38: =SUMIF(INDIRECT(G$36&"!F10:F29"),$B38,INDIRECT(G$36&"!H10:H29")) -> 0 | H38: =SUMIF(INDIRECT(H$36&"!F10:F29"),$B38,INDIRECT(H$36&"!H10:H29")) -> 0 | I38: =SUMIF(INDIRECT(I$36&"!F10:F29"),$B38,INDIRECT(I$36&"!H10:H29")) -> 0 | J38: =SUMIF(INDIRECT(J$36&"!F10:F29"),$B38,INDIRECT(J$36&"!H10:H29")) -> 0 | ... N38: =SUMIF(INDIRECT(N$36&"!F10:F29"),$B38,INDIRECT(N$36&"!H10:H29")) -> 0
B39: Gas | C39: =SUMIF(INDIRECT(C$36&"!F10:F29"),$B39,INDIRECT(C$36&"!H10:H29")) -> 0 | D39: =SUMIF(INDIRECT(D$36&"!F10:F29"),$B39,INDIRECT(D$36&"!H10:H29")) -> 0 | E39: =SUMIF(INDIRECT(E$36&"!F10:F29"),$B39,INDIRECT(E$36&"!H10:H29")) -> 0 | F39: =SUMIF(INDIRECT(F$36&"!F10:F29"),$B39,INDIRECT(F$36&"!H10:H29")) -> 0 | G39: =SUMIF(INDIRECT(G$36&"!F10:F29"),$B39,INDIRECT(G$36&"!H10:H29")) -> 0 | H39: =SUMIF(INDIRECT(H$36&"!F10:F29"),$B39,INDIRECT(H$36&"!H10:H29")) -> 0 | I39: =SUMIF(INDIRECT(I$36&"!F10:F29"),$B39,INDIRECT(I$36&"!H10:H29")) -> 0 | J39: =SUMIF(INDIRECT(J$36&"!F10:F29"),$B39,INDIRECT(J$36&"!H10:H29")) -> 0 | ... N39: =SUMIF(INDIRECT(N$36&"!F10:F29"),$B39,INDIRECT(N$36&"!H10:H29")) -> 0
B40: Internet | C40: =SUMIF(INDIRECT(C$36&"!F10:F29"),$B40,INDIRECT(C$36&"!H10:H29")) -> 0 | D40: =SUMIF(INDIRECT(D$36&"!F10:F29"),$B40,INDIRECT(D$36&"!H10:H29")) -> 0 | E40: =SUMIF(INDIRECT(E$36&"!F10:F29"),$B40,INDIRECT(E$36&"!H10:H29")) -> 0 | F40: =SUMIF(INDIRECT(F$36&"!F10:F29"),$B40,INDIRECT(F$36&"!H10:H29")) -> 0 | G40: =SUMIF(INDIRECT(G$36&"!F10:F29"),$B40,INDIRECT(G$36&"!H10:H29")) -> 0 | H40: =SUMIF(INDIRECT(H$36&"!F10:F29"),$B40,INDIRECT(H$36&"!H10:H29")) -> 0 | I40: =SUMIF(INDIRECT(I$36&"!F10:F29"),$B40,INDIRECT(I$36&"!H10:H29")) -> 0 | J40: =SUMIF(INDIRECT(J$36&"!F10:F29"),$B40,INDIRECT(J$36&"!H10:H29")) -> 0 | ... N40: =SUMIF(INDIRECT(N$36&"!F10:F29"),$B40,INDIRECT(N$36&"!H10:H29")) -> 0
B41: Phone Plan | C41: =SUMIF(INDIRECT(C$36&"!F10:F29"),$B41,INDIRECT(C$36&"!H10:H29")) -> 0 | D41: =SUMIF(INDIRECT(D$36&"!F10:F29"),$B41,INDIRECT(D$36&"!H10:H29")) -> 0 | E41: =SUMIF(INDIRECT(E$36&"!F10:F29"),$B41,INDIRECT(E$36&"!H10:H29")) -> 0 | F41: =SUMIF(INDIRECT(F$36&"!F10:F29"),$B41,INDIRECT(F$36&"!H10:H29")) -> 0 | G41: =SUMIF(INDIRECT(G$36&"!F10:F29"),$B41,INDIRECT(G$36&"!H10:H29")) -> 0 | H41: =SUMIF(INDIRECT(H$36&"!F10:F29"),$B41,INDIRECT(H$36&"!H10:H29")) -> 0 | I41: =SUMIF(INDIRECT(I$36&"!F10:F29"),$B41,INDIRECT(I$36&"!H10:H29")) -> 0 | J41: =SUMIF(INDIRECT(J$36&"!F10:F29"),$B41,INDIRECT(J$36&"!H10:H29")) -> 0 | ... N41: =SUMIF(INDIRECT(N$36&"!F10:F29"),$B41,INDIRECT(N$36&"!H10:H29")) -> 0
B42: Gym Membership | C42: =SUMIF(INDIRECT(C$36&"!F10:F29"),$B42,INDIRECT(C$36&"!H10:H29")) -> 0 | D42: =SUMIF(INDIRECT(D$36&"!F10:F29"),$B42,INDIRECT(D$36&"!H10:H29")) -> 0 | E42: =SUMIF(INDIRECT(E$36&"!F10:F29"),$B42,INDIRECT(E$36&"!H10:H29")) -> 0 | F42: =SUMIF(INDIRECT(F$36&"!F10:F29"),$B42,INDIRECT(F$36&"!H10:H29")) -> 0 | G42: =SUMIF(INDIRECT(G$36&"!F10:F29"),$B42,INDIRECT(G$36&"!H10:H29")) -> 0 | H42: =SUMIF(INDIRECT(H$36&"!F10:F29"),$B42,INDIRECT(H$36&"!H10:H29")) -> 0 | I42: =SUMIF(INDIRECT(I$36&"!F10:F29"),$B42,INDIRECT(I$36&"!H10:H29")) -> 0 | J42: =SUMIF(INDIRECT(J$36&"!F10:F29"),$B42,INDIRECT(J$36&"!H10:H29")) -> 0 | ... N42: =SUMIF(INDIRECT(N$36&"!F10:F29"),$B42,INDIRECT(N$36&"!H10:H29")) -> 0
B43: Car Insurance | C43: =SUMIF(INDIRECT(C$36&"!F10:F29"),$B43,INDIRECT(C$36&"!H10:H29")) -> 0 | D43: =SUMIF(INDIRECT(D$36&"!F10:F29"),$B43,INDIRECT(D$36&"!H10:H29")) -> 0 | E43: =SUMIF(INDIRECT(E$36&"!F10:F29"),$B43,INDIRECT(E$36&"!H10:H29")) -> 0 | F43: =SUMIF(INDIRECT(F$36&"!F10:F29"),$B43,INDIRECT(F$36&"!H10:H29")) -> 0 | G43: =SUMIF(INDIRECT(G$36&"!F10:F29"),$B43,INDIRECT(G$36&"!H10:H29")) -> 0 | H43: =SUMIF(INDIRECT(H$36&"!F10:F29"),$B43,INDIRECT(H$36&"!H10:H29")) -> 0 | I43: =SUMIF(INDIRECT(I$36&"!F10:F29"),$B43,INDIRECT(I$36&"!H10:H29")) -> 0 | J43: =SUMIF(INDIRECT(J$36&"!F10:F29"),$B43,INDIRECT(J$36&"!H10:H29")) -> 0 | ... N43: =SUMIF(INDIRECT(N$36&"!F10:F29"),$B43,INDIRECT(N$36&"!H10:H29")) -> 0
B44: Health Insurance | C44: =SUMIF(INDIRECT(C$36&"!F10:F29"),$B44,INDIRECT(C$36&"!H10:H29")) -> 0 | D44: =SUMIF(INDIRECT(D$36&"!F10:F29"),$B44,INDIRECT(D$36&"!H10:H29")) -> 0 | E44: =SUMIF(INDIRECT(E$36&"!F10:F29"),$B44,INDIRECT(E$36&"!H10:H29")) -> 0 | F44: =SUMIF(INDIRECT(F$36&"!F10:F29"),$B44,INDIRECT(F$36&"!H10:H29")) -> 0 | G44: =SUMIF(INDIRECT(G$36&"!F10:F29"),$B44,INDIRECT(G$36&"!H10:H29")) -> 0 | H44: =SUMIF(INDIRECT(H$36&"!F10:F29"),$B44,INDIRECT(H$36&"!H10:H29")) -> 0 | I44: =SUMIF(INDIRECT(I$36&"!F10:F29"),$B44,INDIRECT(I$36&"!H10:H29")) -> 0 | J44: =SUMIF(INDIRECT(J$36&"!F10:F29"),$B44,INDIRECT(J$36&"!H10:H29")) -> 0 | ... N44: =SUMIF(INDIRECT(N$36&"!F10:F29"),$B44,INDIRECT(N$36&"!H10:H29")) -> 0
C45: =SUMIF(INDIRECT(C$36&"!F10:F29"),$B45,INDIRECT(C$36&"!H10:H29")) -> 0 | D45: =SUMIF(INDIRECT(D$36&"!F10:F29"),$B45,INDIRECT(D$36&"!H10:H29")) -> 0 | E45: =SUMIF(INDIRECT(E$36&"!F10:F29"),$B45,INDIRECT(E$36&"!H10:H29")) -> 0 | F45: =SUMIF(INDIRECT(F$36&"!F10:F29"),$B45,INDIRECT(F$36&"!H10:H29")) -> 0 | G45: =SUMIF(INDIRECT(G$36&"!F10:F29"),$B45,INDIRECT(G$36&"!H10:H29")) -> 0 | H45: =SUMIF(INDIRECT(H$36&"!F10:F29"),$B45,INDIRECT(H$36&"!H10:H29")) -> 0 | I45: =SUMIF(INDIRECT(I$36&"!F10:F29"),$B45,INDIRECT(I$36&"!H10:H29")) -> 0 | J45: =SUMIF(INDIRECT(J$36&"!F10:F29"),$B45,INDIRECT(J$36&"!H10:H29")) -> 0 | ... N45: =SUMIF(INDIRECT(N$36&"!F10:F29"),$B45,INDIRECT(N$36&"!H10:H29")) -> 0
C46: =SUMIF(INDIRECT(C$36&"!F10:F29"),$B46,INDIRECT(C$36&"!H10:H29")) -> 0 | D46: =SUMIF(INDIRECT(D$36&"!F10:F29"),$B46,INDIRECT(D$36&"!H10:H29")) -> 0 | E46: =SUMIF(INDIRECT(E$36&"!F10:F29"),$B46,INDIRECT(E$36&"!H10:H29")) -> 0 | F46: =SUMIF(INDIRECT(F$36&"!F10:F29"),$B46,INDIRECT(F$36&"!H10:H29")) -> 0 | G46: =SUMIF(INDIRECT(G$36&"!F10:F29"),$B46,INDIRECT(G$36&"!H10:H29")) -> 0 | H46: =SUMIF(INDIRECT(H$36&"!F10:F29"),$B46,INDIRECT(H$36&"!H10:H29")) -> 0 | I46: =SUMIF(INDIRECT(I$36&"!F10:F29"),$B46,INDIRECT(I$36&"!H10:H29")) -> 0 | J46: =SUMIF(INDIRECT(J$36&"!F10:F29"),$B46,INDIRECT(J$36&"!H10:H29")) -> 0 | ... N46: =SUMIF(INDIRECT(N$36&"!F10:F29"),$B46,INDIRECT(N$36&"!H10:H29")) -> 0
C47: =SUMIF(INDIRECT(C$36&"!F10:F29"),$B47,INDIRECT(C$36&"!H10:H29")) -> 0 | D47: =SUMIF(INDIRECT(D$36&"!F10:F29"),$B47,INDIRECT(D$36&"!H10:H29")) -> 0 | E47: =SUMIF(INDIRECT(E$36&"!F10:F29"),$B47,INDIRECT(E$36&"!H10:H29")) -> 0 | F47: =SUMIF(INDIRECT(F$36&"!F10:F29"),$B47,INDIRECT(F$36&"!H10:H29")) -> 0 | G47: =SUMIF(INDIRECT(G$36&"!F10:F29"),$B47,INDIRECT(G$36&"!H10:H29")) -> 0 | H47: =SUMIF(INDIRECT(H$36&"!F10:F29"),$B47,INDIRECT(H$36&"!H10:H29")) -> 0 | I47: =SUMIF(INDIRECT(I$36&"!F10:F29"),$B47,INDIRECT(I$36&"!H10:H29")) -> 0 | J47: =SUMIF(INDIRECT(J$36&"!F10:F29"),$B47,INDIRECT(J$36&"!H10:H29")) -> 0 | ... N47: =SUMIF(INDIRECT(N$36&"!F10:F29"),$B47,INDIRECT(N$36&"!H10:H29")) -> 0
C48: =SUMIF(INDIRECT(C$36&"!F10:F29"),$B48,INDIRECT(C$36&"!H10:H29")) -> 0 | D48: =SUMIF(INDIRECT(D$36&"!F10:F29"),$B48,INDIRECT(D$36&"!H10:H29")) -> 0 | E48: =SUMIF(INDIRECT(E$36&"!F10:F29"),$B48,INDIRECT(E$36&"!H10:H29")) -> 0 | F48: =SUMIF(INDIRECT(F$36&"!F10:F29"),$B48,INDIRECT(F$36&"!H10:H29")) -> 0 | G48: =SUMIF(INDIRECT(G$36&"!F10:F29"),$B48,INDIRECT(G$36&"!H10:H29")) -> 0 | H48: =SUMIF(INDIRECT(H$36&"!F10:F29"),$B48,INDIRECT(H$36&"!H10:H29")) -> 0 | I48: =SUMIF(INDIRECT(I$36&"!F10:F29"),$B48,INDIRECT(I$36&"!H10:H29")) -> 0 | J48: =SUMIF(INDIRECT(J$36&"!F10:F29"),$B48,INDIRECT(J$36&"!H10:H29")) -> 0 | ... N48: =SUMIF(INDIRECT(N$36&"!F10:F29"),$B48,INDIRECT(N$36&"!H10:H29")) -> 0
C49: =SUMIF(INDIRECT(C$36&"!F10:F29"),$B49,INDIRECT(C$36&"!H10:H29")) -> 0 | D49: =SUMIF(INDIRECT(D$36&"!F10:F29"),$B49,INDIRECT(D$36&"!H10:H29")) -> 0 | E49: =SUMIF(INDIRECT(E$36&"!F10:F29"),$B49,INDIRECT(E$36&"!H10:H29")) -> 0 | F49: =SUMIF(INDIRECT(F$36&"!F10:F29"),$B49,INDIRECT(F$36&"!H10:H29")) -> 0 | G49: =SUMIF(INDIRECT(G$36&"!F10:F29"),$B49,INDIRECT(G$36&"!H10:H29")) -> 0 | H49: =SUMIF(INDIRECT(H$36&"!F10:F29"),$B49,INDIRECT(H$36&"!H10:H29")) -> 0 | I49: =SUMIF(INDIRECT(I$36&"!F10:F29"),$B49,INDIRECT(I$36&"!H10:H29")) -> 0 | J49: =SUMIF(INDIRECT(J$36&"!F10:F29"),$B49,INDIRECT(J$36&"!H10:H29")) -> 0 | ... N49: =SUMIF(INDIRECT(N$36&"!F10:F29"),$B49,INDIRECT(N$36&"!H10:H29")) -> 0
C50: =SUMIF(INDIRECT(C$36&"!F10:F29"),$B50,INDIRECT(C$36&"!H10:H29")) -> 0 | D50: =SUMIF(INDIRECT(D$36&"!F10:F29"),$B50,INDIRECT(D$36&"!H10:H29")) -> 0 | E50: =SUMIF(INDIRECT(E$36&"!F10:F29"),$B50,INDIRECT(E$36&"!H10:H29")) -> 0 | F50: =SUMIF(INDIRECT(F$36&"!F10:F29"),$B50,INDIRECT(F$36&"!H10:H29")) -> 0 | G50: =SUMIF(INDIRECT(G$36&"!F10:F29"),$B50,INDIRECT(G$36&"!H10:H29")) -> 0 | H50: =SUMIF(INDIRECT(H$36&"!F10:F29"),$B50,INDIRECT(H$36&"!H10:H29")) -> 0 | I50: =SUMIF(INDIRECT(I$36&"!F10:F29"),$B50,INDIRECT(I$36&"!H10:H29")) -> 0 | J50: =SUMIF(INDIRECT(J$36&"!F10:F29"),$B50,INDIRECT(J$36&"!H10:H29")) -> 0 | ... N50: =SUMIF(INDIRECT(N$36&"!F10:F29"),$B50,INDIRECT(N$36&"!H10:H29")) -> 0
C51: =SUMIF(INDIRECT(C$36&"!F10:F29"),$B51,INDIRECT(C$36&"!H10:H29")) -> 0 | D51: =SUMIF(INDIRECT(D$36&"!F10:F29"),$B51,INDIRECT(D$36&"!H10:H29")) -> 0 | E51: =SUMIF(INDIRECT(E$36&"!F10:F29"),$B51,INDIRECT(E$36&"!H10:H29")) -> 0 | F51: =SUMIF(INDIRECT(F$36&"!F10:F29"),$B51,INDIRECT(F$36&"!H10:H29")) -> 0 | G51: =SUMIF(INDIRECT(G$36&"!F10:F29"),$B51,INDIRECT(G$36&"!H10:H29")) -> 0 | H51: =SUMIF(INDIRECT(H$36&"!F10:F29"),$B51,INDIRECT(H$36&"!H10:H29")) -> 0 | I51: =SUMIF(INDIRECT(I$36&"!F10:F29"),$B51,INDIRECT(I$36&"!H10:H29")) -> 0 | J51: =SUMIF(INDIRECT(J$36&"!F10:F29"),$B51,INDIRECT(J$36&"!H10:H29")) -> 0 | ... N51: =SUMIF(INDIRECT(N$36&"!F10:F29"),$B51,INDIRECT(N$36&"!H10:H29")) -> 0
C52: =SUMIF(INDIRECT(C$36&"!F10:F29"),$B52,INDIRECT(C$36&"!H10:H29")) -> 0 | D52: =SUMIF(INDIRECT(D$36&"!F10:F29"),$B52,INDIRECT(D$36&"!H10:H29")) -> 0 | E52: =SUMIF(INDIRECT(E$36&"!F10:F29"),$B52,INDIRECT(E$36&"!H10:H29")) -> 0 | F52: =SUMIF(INDIRECT(F$36&"!F10:F29"),$B52,INDIRECT(F$36&"!H10:H29")) -> 0 | G52: =SUMIF(INDIRECT(G$36&"!F10:F29"),$B52,INDIRECT(G$36&"!H10:H29")) -> 0 | H52: =SUMIF(INDIRECT(H$36&"!F10:F29"),$B52,INDIRECT(H$36&"!H10:H29")) -> 0 | I52: =SUMIF(INDIRECT(I$36&"!F10:F29"),$B52,INDIRECT(I$36&"!H10:H29")) -> 0 | J52: =SUMIF(INDIRECT(J$36&"!F10:F29"),$B52,INDIRECT(J$36&"!H10:H29")) -> 0 | ... N52: =SUMIF(INDIRECT(N$36&"!F10:F29"),$B52,INDIRECT(N$36&"!H10:H29")) -> 0
C53: =SUMIF(INDIRECT(C$36&"!F10:F29"),$B53,INDIRECT(C$36&"!H10:H29")) -> 0 | D53: =SUMIF(INDIRECT(D$36&"!F10:F29"),$B53,INDIRECT(D$36&"!H10:H29")) -> 0 | E53: =SUMIF(INDIRECT(E$36&"!F10:F29"),$B53,INDIRECT(E$36&"!H10:H29")) -> 0 | F53: =SUMIF(INDIRECT(F$36&"!F10:F29"),$B53,INDIRECT(F$36&"!H10:H29")) -> 0 | G53: =SUMIF(INDIRECT(G$36&"!F10:F29"),$B53,INDIRECT(G$36&"!H10:H29")) -> 0 | H53: =SUMIF(INDIRECT(H$36&"!F10:F29"),$B53,INDIRECT(H$36&"!H10:H29")) -> 0 | I53: =SUMIF(INDIRECT(I$36&"!F10:F29"),$B53,INDIRECT(I$36&"!H10:H29")) -> 0 | J53: =SUMIF(INDIRECT(J$36&"!F10:F29"),$B53,INDIRECT(J$36&"!H10:H29")) -> 0 | ... N53: =SUMIF(INDIRECT(N$36&"!F10:F29"),$B53,INDIRECT(N$36&"!H10:H29")) -> 0
C54: =SUMIF(INDIRECT(C$36&"!F10:F29"),$B54,INDIRECT(C$36&"!H10:H29")) -> 0 | D54: =SUMIF(INDIRECT(D$36&"!F10:F29"),$B54,INDIRECT(D$36&"!H10:H29")) -> 0 | E54: =SUMIF(INDIRECT(E$36&"!F10:F29"),$B54,INDIRECT(E$36&"!H10:H29")) -> 0 | F54: =SUMIF(INDIRECT(F$36&"!F10:F29"),$B54,INDIRECT(F$36&"!H10:H29")) -> 0 | G54: =SUMIF(INDIRECT(G$36&"!F10:F29"),$B54,INDIRECT(G$36&"!H10:H29")) -> 0 | H54: =SUMIF(INDIRECT(H$36&"!F10:F29"),$B54,INDIRECT(H$36&"!H10:H29")) -> 0 | I54: =SUMIF(INDIRECT(I$36&"!F10:F29"),$B54,INDIRECT(I$36&"!H10:H29")) -> 0 | J54: =SUMIF(INDIRECT(J$36&"!F10:F29"),$B54,INDIRECT(J$36&"!H10:H29")) -> 0 | ... N54: =SUMIF(INDIRECT(N$36&"!F10:F29"),$B54,INDIRECT(N$36&"!H10:H29")) -> 0
C55: =SUMIF(INDIRECT(C$36&"!F10:F29"),$B55,INDIRECT(C$36&"!H10:H29")) -> 0 | D55: =SUMIF(INDIRECT(D$36&"!F10:F29"),$B55,INDIRECT(D$36&"!H10:H29")) -> 0 | E55: =SUMIF(INDIRECT(E$36&"!F10:F29"),$B55,INDIRECT(E$36&"!H10:H29")) -> 0 | F55: =SUMIF(INDIRECT(F$36&"!F10:F29"),$B55,INDIRECT(F$36&"!H10:H29")) -> 0 | G55: =SUMIF(INDIRECT(G$36&"!F10:F29"),$B55,INDIRECT(G$36&"!H10:H29")) -> 0 | H55: =SUMIF(INDIRECT(H$36&"!F10:F29"),$B55,INDIRECT(H$36&"!H10:H29")) -> 0 | I55: =SUMIF(INDIRECT(I$36&"!F10:F29"),$B55,INDIRECT(I$36&"!H10:H29")) -> 0 | J55: =SUMIF(INDIRECT(J$36&"!F10:F29"),$B55,INDIRECT(J$36&"!H10:H29")) -> 0 | ... N55: =SUMIF(INDIRECT(N$36&"!F10:F29"),$B55,INDIRECT(N$36&"!H10:H29")) -> 0
C56: =SUMIF(INDIRECT(C$36&"!F10:F29"),$B56,INDIRECT(C$36&"!H10:H29")) -> 0 | D56: =SUMIF(INDIRECT(D$36&"!F10:F29"),$B56,INDIRECT(D$36&"!H10:H29")) -> 0 | E56: =SUMIF(INDIRECT(E$36&"!F10:F29"),$B56,INDIRECT(E$36&"!H10:H29")) -> 0 | F56: =SUMIF(INDIRECT(F$36&"!F10:F29"),$B56,INDIRECT(F$36&"!H10:H29")) -> 0 | G56: =SUMIF(INDIRECT(G$36&"!F10:F29"),$B56,INDIRECT(G$36&"!H10:H29")) -> 0 | H56: =SUMIF(INDIRECT(H$36&"!F10:F29"),$B56,INDIRECT(H$36&"!H10:H29")) -> 0 | I56: =SUMIF(INDIRECT(I$36&"!F10:F29"),$B56,INDIRECT(I$36&"!H10:H29")) -> 0 | J56: =SUMIF(INDIRECT(J$36&"!F10:F29"),$B56,INDIRECT(J$36&"!H10:H29")) -> 0 | ... N56: =SUMIF(INDIRECT(N$36&"!F10:F29"),$B56,INDIRECT(N$36&"!H10:H29")) -> 0
B57: Total Bills | C57: =SUM(C37:C56) -> 0 | D57: =SUM(D37:D56) -> 0 | E57: =SUM(E37:E56) -> 0 | F57: =SUM(F37:F56) -> 0 | G57: =SUM(G37:G56) -> 0 | H57: =SUM(H37:H56) -> 0 | I57: =SUM(I37:I56) -> 0 | J57: =SUM(J37:J56) -> 0 | ... N57: =SUM(N37:N56) -> 0
B59: Expenses
B60: Name | C60: JAN | D60: FEB | E60: MAR | F60: APR | G60: MAY | H60: JUN | I60: JUL | J60: AUG | K60: SEP | L60: OCT | M60: NOV | N60: DEC
B61: Groceries | C61: =SUMIF(INDIRECT(C$60&"!J10:J29"),$B61,INDIRECT(C$60&"!L10:L29")) -> 0 | D61: =SUMIF(INDIRECT(D$60&"!J10:J29"),$B61,INDIRECT(D$60&"!L10:L29")) -> 0 | E61: =SUMIF(INDIRECT(E$60&"!J10:J29"),$B61,INDIRECT(E$60&"!L10:L29")) -> 0 | F61: =SUMIF(INDIRECT(F$60&"!J10:J29"),$B61,INDIRECT(F$60&"!L10:L29")) -> 0 | G61: =SUMIF(INDIRECT(G$60&"!J10:J29"),$B61,INDIRECT(G$60&"!L10:L29")) -> 0 | H61: =SUMIF(INDIRECT(H$60&"!J10:J29"),$B61,INDIRECT(H$60&"!L10:L29")) -> 0 | I61: =SUMIF(INDIRECT(I$60&"!J10:J29"),$B61,INDIRECT(I$60&"!L10:L29")) -> 0 | J61: =SUMIF(INDIRECT(J$60&"!J10:J29"),$B61,INDIRECT(J$60&"!L10:L29")) -> 0 | ... N61: =SUMIF(INDIRECT(N$60&"!J10:J29"),$B61,INDIRECT(N$60&"!L10:L29")) -> 0
B62: Dining Out | C62: =SUMIF(INDIRECT(C$60&"!J10:J29"),$B62,INDIRECT(C$60&"!L10:L29")) -> 0 | D62: =SUMIF(INDIRECT(D$60&"!J10:J29"),$B62,INDIRECT(D$60&"!L10:L29")) -> 0 | E62: =SUMIF(INDIRECT(E$60&"!J10:J29"),$B62,INDIRECT(E$60&"!L10:L29")) -> 0 | F62: =SUMIF(INDIRECT(F$60&"!J10:J29"),$B62,INDIRECT(F$60&"!L10:L29")) -> 0 | G62: =SUMIF(INDIRECT(G$60&"!J10:J29"),$B62,INDIRECT(G$60&"!L10:L29")) -> 0 | H62: =SUMIF(INDIRECT(H$60&"!J10:J29"),$B62,INDIRECT(H$60&"!L10:L29")) -> 0 | I62: =SUMIF(INDIRECT(I$60&"!J10:J29"),$B62,INDIRECT(I$60&"!L10:L29")) -> 0 | J62: =SUMIF(INDIRECT(J$60&"!J10:J29"),$B62,INDIRECT(J$60&"!L10:L29")) -> 0 | ... N62: =SUMIF(INDIRECT(N$60&"!J10:J29"),$B62,INDIRECT(N$60&"!L10:L29")) -> 0
B63: Fuel | C63: =SUMIF(INDIRECT(C$60&"!J10:J29"),$B63,INDIRECT(C$60&"!L10:L29")) -> 0 | D63: =SUMIF(INDIRECT(D$60&"!J10:J29"),$B63,INDIRECT(D$60&"!L10:L29")) -> 0 | E63: =SUMIF(INDIRECT(E$60&"!J10:J29"),$B63,INDIRECT(E$60&"!L10:L29")) -> 0 | F63: =SUMIF(INDIRECT(F$60&"!J10:J29"),$B63,INDIRECT(F$60&"!L10:L29")) -> 0 | G63: =SUMIF(INDIRECT(G$60&"!J10:J29"),$B63,INDIRECT(G$60&"!L10:L29")) -> 0 | H63: =SUMIF(INDIRECT(H$60&"!J10:J29"),$B63,INDIRECT(H$60&"!L10:L29")) -> 0 | I63: =SUMIF(INDIRECT(I$60&"!J10:J29"),$B63,INDIRECT(I$60&"!L10:L29")) -> 0 | J63: =SUMIF(INDIRECT(J$60&"!J10:J29"),$B63,INDIRECT(J$60&"!L10:L29")) -> 0 | ... N63: =SUMIF(INDIRECT(N$60&"!J10:J29"),$B63,INDIRECT(N$60&"!L10:L29")) -> 0
B64: Shopping | C64: =SUMIF(INDIRECT(C$60&"!J10:J29"),$B64,INDIRECT(C$60&"!L10:L29")) -> 0 | D64: =SUMIF(INDIRECT(D$60&"!J10:J29"),$B64,INDIRECT(D$60&"!L10:L29")) -> 0 | E64: =SUMIF(INDIRECT(E$60&"!J10:J29"),$B64,INDIRECT(E$60&"!L10:L29")) -> 0 | F64: =SUMIF(INDIRECT(F$60&"!J10:J29"),$B64,INDIRECT(F$60&"!L10:L29")) -> 0 | G64: =SUMIF(INDIRECT(G$60&"!J10:J29"),$B64,INDIRECT(G$60&"!L10:L29")) -> 0 | H64: =SUMIF(INDIRECT(H$60&"!J10:J29"),$B64,INDIRECT(H$60&"!L10:L29")) -> 0 | I64: =SUMIF(INDIRECT(I$60&"!J10:J29"),$B64,INDIRECT(I$60&"!L10:L29")) -> 0 | J64: =SUMIF(INDIRECT(J$60&"!J10:J29"),$B64,INDIRECT(J$60&"!L10:L29")) -> 0 | ... N64: =SUMIF(INDIRECT(N$60&"!J10:J29"),$B64,INDIRECT(N$60&"!L10:L29")) -> 0
B65: Beauty | C65: =SUMIF(INDIRECT(C$60&"!J10:J29"),$B65,INDIRECT(C$60&"!L10:L29")) -> 0 | D65: =SUMIF(INDIRECT(D$60&"!J10:J29"),$B65,INDIRECT(D$60&"!L10:L29")) -> 0 | E65: =SUMIF(INDIRECT(E$60&"!J10:J29"),$B65,INDIRECT(E$60&"!L10:L29")) -> 0 | F65: =SUMIF(INDIRECT(F$60&"!J10:J29"),$B65,INDIRECT(F$60&"!L10:L29")) -> 0 | G65: =SUMIF(INDIRECT(G$60&"!J10:J29"),$B65,INDIRECT(G$60&"!L10:L29")) -> 0 | H65: =SUMIF(INDIRECT(H$60&"!J10:J29"),$B65,INDIRECT(H$60&"!L10:L29")) -> 0 | I65: =SUMIF(INDIRECT(I$60&"!J10:J29"),$B65,INDIRECT(I$60&"!L10:L29")) -> 0 | J65: =SUMIF(INDIRECT(J$60&"!J10:J29"),$B65,INDIRECT(J$60&"!L10:L29")) -> 0 | ... N65: =SUMIF(INDIRECT(N$60&"!J10:J29"),$B65,INDIRECT(N$60&"!L10:L29")) -> 0
B66: Entertainment | C66: =SUMIF(INDIRECT(C$60&"!J10:J29"),$B66,INDIRECT(C$60&"!L10:L29")) -> 0 | D66: =SUMIF(INDIRECT(D$60&"!J10:J29"),$B66,INDIRECT(D$60&"!L10:L29")) -> 0 | E66: =SUMIF(INDIRECT(E$60&"!J10:J29"),$B66,INDIRECT(E$60&"!L10:L29")) -> 0 | F66: =SUMIF(INDIRECT(F$60&"!J10:J29"),$B66,INDIRECT(F$60&"!L10:L29")) -> 0 | G66: =SUMIF(INDIRECT(G$60&"!J10:J29"),$B66,INDIRECT(G$60&"!L10:L29")) -> 0 | H66: =SUMIF(INDIRECT(H$60&"!J10:J29"),$B66,INDIRECT(H$60&"!L10:L29")) -> 0 | I66: =SUMIF(INDIRECT(I$60&"!J10:J29"),$B66,INDIRECT(I$60&"!L10:L29")) -> 0 | J66: =SUMIF(INDIRECT(J$60&"!J10:J29"),$B66,INDIRECT(J$60&"!L10:L29")) -> 0 | ... N66: =SUMIF(INDIRECT(N$60&"!J10:J29"),$B66,INDIRECT(N$60&"!L10:L29")) -> 0
B67: Travel | C67: =SUMIF(INDIRECT(C$60&"!J10:J29"),$B67,INDIRECT(C$60&"!L10:L29")) -> 0 | D67: =SUMIF(INDIRECT(D$60&"!J10:J29"),$B67,INDIRECT(D$60&"!L10:L29")) -> 0 | E67: =SUMIF(INDIRECT(E$60&"!J10:J29"),$B67,INDIRECT(E$60&"!L10:L29")) -> 0 | F67: =SUMIF(INDIRECT(F$60&"!J10:J29"),$B67,INDIRECT(F$60&"!L10:L29")) -> 0 | G67: =SUMIF(INDIRECT(G$60&"!J10:J29"),$B67,INDIRECT(G$60&"!L10:L29")) -> 0 | H67: =SUMIF(INDIRECT(H$60&"!J10:J29"),$B67,INDIRECT(H$60&"!L10:L29")) -> 0 | I67: =SUMIF(INDIRECT(I$60&"!J10:J29"),$B67,INDIRECT(I$60&"!L10:L29")) -> 0 | J67: =SUMIF(INDIRECT(J$60&"!J10:J29"),$B67,INDIRECT(J$60&"!L10:L29")) -> 0 | ... N67: =SUMIF(INDIRECT(N$60&"!J10:J29"),$B67,INDIRECT(N$60&"!L10:L29")) -> 0
B68: Gifts | C68: =SUMIF(INDIRECT(C$60&"!J10:J29"),$B68,INDIRECT(C$60&"!L10:L29")) -> 0 | D68: =SUMIF(INDIRECT(D$60&"!J10:J29"),$B68,INDIRECT(D$60&"!L10:L29")) -> 0 | E68: =SUMIF(INDIRECT(E$60&"!J10:J29"),$B68,INDIRECT(E$60&"!L10:L29")) -> 0 | F68: =SUMIF(INDIRECT(F$60&"!J10:J29"),$B68,INDIRECT(F$60&"!L10:L29")) -> 0 | G68: =SUMIF(INDIRECT(G$60&"!J10:J29"),$B68,INDIRECT(G$60&"!L10:L29")) -> 0 | H68: =SUMIF(INDIRECT(H$60&"!J10:J29"),$B68,INDIRECT(H$60&"!L10:L29")) -> 0 | I68: =SUMIF(INDIRECT(I$60&"!J10:J29"),$B68,INDIRECT(I$60&"!L10:L29")) -> 0 | J68: =SUMIF(INDIRECT(J$60&"!J10:J29"),$B68,INDIRECT(J$60&"!L10:L29")) -> 0 | ... N68: =SUMIF(INDIRECT(N$60&"!J10:J29"),$B68,INDIRECT(N$60&"!L10:L29")) -> 0
B69: Health | C69: =SUMIF(INDIRECT(C$60&"!J10:J29"),$B69,INDIRECT(C$60&"!L10:L29")) -> 0 | D69: =SUMIF(INDIRECT(D$60&"!J10:J29"),$B69,INDIRECT(D$60&"!L10:L29")) -> 0 | E69: =SUMIF(INDIRECT(E$60&"!J10:J29"),$B69,INDIRECT(E$60&"!L10:L29")) -> 0 | F69: =SUMIF(INDIRECT(F$60&"!J10:J29"),$B69,INDIRECT(F$60&"!L10:L29")) -> 0 | G69: =SUMIF(INDIRECT(G$60&"!J10:J29"),$B69,INDIRECT(G$60&"!L10:L29")) -> 0 | H69: =SUMIF(INDIRECT(H$60&"!J10:J29"),$B69,INDIRECT(H$60&"!L10:L29")) -> 0 | I69: =SUMIF(INDIRECT(I$60&"!J10:J29"),$B69,INDIRECT(I$60&"!L10:L29")) -> 0 | J69: =SUMIF(INDIRECT(J$60&"!J10:J29"),$B69,INDIRECT(J$60&"!L10:L29")) -> 0 | ... N69: =SUMIF(INDIRECT(N$60&"!J10:J29"),$B69,INDIRECT(N$60&"!L10:L29")) -> 0
B70: Pets | C70: =SUMIF(INDIRECT(C$60&"!J10:J29"),$B70,INDIRECT(C$60&"!L10:L29")) -> 0 | D70: =SUMIF(INDIRECT(D$60&"!J10:J29"),$B70,INDIRECT(D$60&"!L10:L29")) -> 0 | E70: =SUMIF(INDIRECT(E$60&"!J10:J29"),$B70,INDIRECT(E$60&"!L10:L29")) -> 0 | F70: =SUMIF(INDIRECT(F$60&"!J10:J29"),$B70,INDIRECT(F$60&"!L10:L29")) -> 0 | G70: =SUMIF(INDIRECT(G$60&"!J10:J29"),$B70,INDIRECT(G$60&"!L10:L29")) -> 0 | H70: =SUMIF(INDIRECT(H$60&"!J10:J29"),$B70,INDIRECT(H$60&"!L10:L29")) -> 0 | I70: =SUMIF(INDIRECT(I$60&"!J10:J29"),$B70,INDIRECT(I$60&"!L10:L29")) -> 0 | J70: =SUMIF(INDIRECT(J$60&"!J10:J29"),$B70,INDIRECT(J$60&"!L10:L29")) -> 0 | ... N70: =SUMIF(INDIRECT(N$60&"!J10:J29"),$B70,INDIRECT(N$60&"!L10:L29")) -> 0
B71: Custom Expense 1 | C71: =SUMIF(INDIRECT(C$60&"!J10:J29"),$B71,INDIRECT(C$60&"!L10:L29")) -> 0 | D71: =SUMIF(INDIRECT(D$60&"!J10:J29"),$B71,INDIRECT(D$60&"!L10:L29")) -> 0 | E71: =SUMIF(INDIRECT(E$60&"!J10:J29"),$B71,INDIRECT(E$60&"!L10:L29")) -> 0 | F71: =SUMIF(INDIRECT(F$60&"!J10:J29"),$B71,INDIRECT(F$60&"!L10:L29")) -> 0 | G71: =SUMIF(INDIRECT(G$60&"!J10:J29"),$B71,INDIRECT(G$60&"!L10:L29")) -> 0 | H71: =SUMIF(INDIRECT(H$60&"!J10:J29"),$B71,INDIRECT(H$60&"!L10:L29")) -> 0 | I71: =SUMIF(INDIRECT(I$60&"!J10:J29"),$B71,INDIRECT(I$60&"!L10:L29")) -> 0 | J71: =SUMIF(INDIRECT(J$60&"!J10:J29"),$B71,INDIRECT(J$60&"!L10:L29")) -> 0 | ... N71: =SUMIF(INDIRECT(N$60&"!J10:J29"),$B71,INDIRECT(N$60&"!L10:L29")) -> 0
B72: Custom Expense 2 | C72: =SUMIF(INDIRECT(C$60&"!J10:J29"),$B72,INDIRECT(C$60&"!L10:L29")) -> 0 | D72: =SUMIF(INDIRECT(D$60&"!J10:J29"),$B72,INDIRECT(D$60&"!L10:L29")) -> 0 | E72: =SUMIF(INDIRECT(E$60&"!J10:J29"),$B72,INDIRECT(E$60&"!L10:L29")) -> 0 | F72: =SUMIF(INDIRECT(F$60&"!J10:J29"),$B72,INDIRECT(F$60&"!L10:L29")) -> 0 | G72: =SUMIF(INDIRECT(G$60&"!J10:J29"),$B72,INDIRECT(G$60&"!L10:L29")) -> 0 | H72: =SUMIF(INDIRECT(H$60&"!J10:J29"),$B72,INDIRECT(H$60&"!L10:L29")) -> 0 | I72: =SUMIF(INDIRECT(I$60&"!J10:J29"),$B72,INDIRECT(I$60&"!L10:L29")) -> 0 | J72: =SUMIF(INDIRECT(J$60&"!J10:J29"),$B72,INDIRECT(J$60&"!L10:L29")) -> 0 | ... N72: =SUMIF(INDIRECT(N$60&"!J10:J29"),$B72,INDIRECT(N$60&"!L10:L29")) -> 0
C73: =SUMIF(INDIRECT(C$60&"!J10:J29"),$B73,INDIRECT(C$60&"!L10:L29")) -> 0 | D73: =SUMIF(INDIRECT(D$60&"!J10:J29"),$B73,INDIRECT(D$60&"!L10:L29")) -> 0 | E73: =SUMIF(INDIRECT(E$60&"!J10:J29"),$B73,INDIRECT(E$60&"!L10:L29")) -> 0 | F73: =SUMIF(INDIRECT(F$60&"!J10:J29"),$B73,INDIRECT(F$60&"!L10:L29")) -> 0 | G73: =SUMIF(INDIRECT(G$60&"!J10:J29"),$B73,INDIRECT(G$60&"!L10:L29")) -> 0 | H73: =SUMIF(INDIRECT(H$60&"!J10:J29"),$B73,INDIRECT(H$60&"!L10:L29")) -> 0 | I73: =SUMIF(INDIRECT(I$60&"!J10:J29"),$B73,INDIRECT(I$60&"!L10:L29")) -> 0 | J73: =SUMIF(INDIRECT(J$60&"!J10:J29"),$B73,INDIRECT(J$60&"!L10:L29")) -> 0 | ... N73: =SUMIF(INDIRECT(N$60&"!J10:J29"),$B73,INDIRECT(N$60&"!L10:L29")) -> 0
C74: =SUMIF(INDIRECT(C$60&"!J10:J29"),$B74,INDIRECT(C$60&"!L10:L29")) -> 0 | D74: =SUMIF(INDIRECT(D$60&"!J10:J29"),$B74,INDIRECT(D$60&"!L10:L29")) -> 0 | E74: =SUMIF(INDIRECT(E$60&"!J10:J29"),$B74,INDIRECT(E$60&"!L10:L29")) -> 0 | F74: =SUMIF(INDIRECT(F$60&"!J10:J29"),$B74,INDIRECT(F$60&"!L10:L29")) -> 0 | G74: =SUMIF(INDIRECT(G$60&"!J10:J29"),$B74,INDIRECT(G$60&"!L10:L29")) -> 0 | H74: =SUMIF(INDIRECT(H$60&"!J10:J29"),$B74,INDIRECT(H$60&"!L10:L29")) -> 0 | I74: =SUMIF(INDIRECT(I$60&"!J10:J29"),$B74,INDIRECT(I$60&"!L10:L29")) -> 0 | J74: =SUMIF(INDIRECT(J$60&"!J10:J29"),$B74,INDIRECT(J$60&"!L10:L29")) -> 0 | ... N74: =SUMIF(INDIRECT(N$60&"!J10:J29"),$B74,INDIRECT(N$60&"!L10:L29")) -> 0
C75: =SUMIF(INDIRECT(C$60&"!J10:J29"),$B75,INDIRECT(C$60&"!L10:L29")) -> 0 | D75: =SUMIF(INDIRECT(D$60&"!J10:J29"),$B75,INDIRECT(D$60&"!L10:L29")) -> 0 | E75: =SUMIF(INDIRECT(E$60&"!J10:J29"),$B75,INDIRECT(E$60&"!L10:L29")) -> 0 | F75: =SUMIF(INDIRECT(F$60&"!J10:J29"),$B75,INDIRECT(F$60&"!L10:L29")) -> 0 | G75: =SUMIF(INDIRECT(G$60&"!J10:J29"),$B75,INDIRECT(G$60&"!L10:L29")) -> 0 | H75: =SUMIF(INDIRECT(H$60&"!J10:J29"),$B75,INDIRECT(H$60&"!L10:L29")) -> 0 | I75: =SUMIF(INDIRECT(I$60&"!J10:J29"),$B75,INDIRECT(I$60&"!L10:L29")) -> 0 | J75: =SUMIF(INDIRECT(J$60&"!J10:J29"),$B75,INDIRECT(J$60&"!L10:L29")) -> 0 | ... N75: =SUMIF(INDIRECT(N$60&"!J10:J29"),$B75,INDIRECT(N$60&"!L10:L29")) -> 0
C76: =SUMIF(INDIRECT(C$60&"!J10:J29"),$B76,INDIRECT(C$60&"!L10:L29")) -> 0 | D76: =SUMIF(INDIRECT(D$60&"!J10:J29"),$B76,INDIRECT(D$60&"!L10:L29")) -> 0 | E76: =SUMIF(INDIRECT(E$60&"!J10:J29"),$B76,INDIRECT(E$60&"!L10:L29")) -> 0 | F76: =SUMIF(INDIRECT(F$60&"!J10:J29"),$B76,INDIRECT(F$60&"!L10:L29")) -> 0 | G76: =SUMIF(INDIRECT(G$60&"!J10:J29"),$B76,INDIRECT(G$60&"!L10:L29")) -> 0 | H76: =SUMIF(INDIRECT(H$60&"!J10:J29"),$B76,INDIRECT(H$60&"!L10:L29")) -> 0 | I76: =SUMIF(INDIRECT(I$60&"!J10:J29"),$B76,INDIRECT(I$60&"!L10:L29")) -> 0 | J76: =SUMIF(INDIRECT(J$60&"!J10:J29"),$B76,INDIRECT(J$60&"!L10:L29")) -> 0 | ... N76: =SUMIF(INDIRECT(N$60&"!J10:J29"),$B76,INDIRECT(N$60&"!L10:L29")) -> 0
C77: =SUMIF(INDIRECT(C$60&"!J10:J29"),$B77,INDIRECT(C$60&"!L10:L29")) -> 0 | D77: =SUMIF(INDIRECT(D$60&"!J10:J29"),$B77,INDIRECT(D$60&"!L10:L29")) -> 0 | E77: =SUMIF(INDIRECT(E$60&"!J10:J29"),$B77,INDIRECT(E$60&"!L10:L29")) -> 0 | F77: =SUMIF(INDIRECT(F$60&"!J10:J29"),$B77,INDIRECT(F$60&"!L10:L29")) -> 0 | G77: =SUMIF(INDIRECT(G$60&"!J10:J29"),$B77,INDIRECT(G$60&"!L10:L29")) -> 0 | H77: =SUMIF(INDIRECT(H$60&"!J10:J29"),$B77,INDIRECT(H$60&"!L10:L29")) -> 0 | I77: =SUMIF(INDIRECT(I$60&"!J10:J29"),$B77,INDIRECT(I$60&"!L10:L29")) -> 0 | J77: =SUMIF(INDIRECT(J$60&"!J10:J29"),$B77,INDIRECT(J$60&"!L10:L29")) -> 0 | ... N77: =SUMIF(INDIRECT(N$60&"!J10:J29"),$B77,INDIRECT(N$60&"!L10:L29")) -> 0
C78: =SUMIF(INDIRECT(C$60&"!J10:J29"),$B78,INDIRECT(C$60&"!L10:L29")) -> 0 | D78: =SUMIF(INDIRECT(D$60&"!J10:J29"),$B78,INDIRECT(D$60&"!L10:L29")) -> 0 | E78: =SUMIF(INDIRECT(E$60&"!J10:J29"),$B78,INDIRECT(E$60&"!L10:L29")) -> 0 | F78: =SUMIF(INDIRECT(F$60&"!J10:J29"),$B78,INDIRECT(F$60&"!L10:L29")) -> 0 | G78: =SUMIF(INDIRECT(G$60&"!J10:J29"),$B78,INDIRECT(G$60&"!L10:L29")) -> 0 | H78: =SUMIF(INDIRECT(H$60&"!J10:J29"),$B78,INDIRECT(H$60&"!L10:L29")) -> 0 | I78: =SUMIF(INDIRECT(I$60&"!J10:J29"),$B78,INDIRECT(I$60&"!L10:L29")) -> 0 | J78: =SUMIF(INDIRECT(J$60&"!J10:J29"),$B78,INDIRECT(J$60&"!L10:L29")) -> 0 | ... N78: =SUMIF(INDIRECT(N$60&"!J10:J29"),$B78,INDIRECT(N$60&"!L10:L29")) -> 0
C79: =SUMIF(INDIRECT(C$60&"!J10:J29"),$B79,INDIRECT(C$60&"!L10:L29")) -> 0 | D79: =SUMIF(INDIRECT(D$60&"!J10:J29"),$B79,INDIRECT(D$60&"!L10:L29")) -> 0 | E79: =SUMIF(INDIRECT(E$60&"!J10:J29"),$B79,INDIRECT(E$60&"!L10:L29")) -> 0 | F79: =SUMIF(INDIRECT(F$60&"!J10:J29"),$B79,INDIRECT(F$60&"!L10:L29")) -> 0 | G79: =SUMIF(INDIRECT(G$60&"!J10:J29"),$B79,INDIRECT(G$60&"!L10:L29")) -> 0 | H79: =SUMIF(INDIRECT(H$60&"!J10:J29"),$B79,INDIRECT(H$60&"!L10:L29")) -> 0 | I79: =SUMIF(INDIRECT(I$60&"!J10:J29"),$B79,INDIRECT(I$60&"!L10:L29")) -> 0 | J79: =SUMIF(INDIRECT(J$60&"!J10:J29"),$B79,INDIRECT(J$60&"!L10:L29")) -> 0 | ... N79: =SUMIF(INDIRECT(N$60&"!J10:J29"),$B79,INDIRECT(N$60&"!L10:L29")) -> 0
C80: =SUMIF(INDIRECT(C$60&"!J10:J29"),$B80,INDIRECT(C$60&"!L10:L29")) -> 0 | D80: =SUMIF(INDIRECT(D$60&"!J10:J29"),$B80,INDIRECT(D$60&"!L10:L29")) -> 0 | E80: =SUMIF(INDIRECT(E$60&"!J10:J29"),$B80,INDIRECT(E$60&"!L10:L29")) -> 0 | F80: =SUMIF(INDIRECT(F$60&"!J10:J29"),$B80,INDIRECT(F$60&"!L10:L29")) -> 0 | G80: =SUMIF(INDIRECT(G$60&"!J10:J29"),$B80,INDIRECT(G$60&"!L10:L29")) -> 0 | H80: =SUMIF(INDIRECT(H$60&"!J10:J29"),$B80,INDIRECT(H$60&"!L10:L29")) -> 0 | I80: =SUMIF(INDIRECT(I$60&"!J10:J29"),$B80,INDIRECT(I$60&"!L10:L29")) -> 0 | J80: =SUMIF(INDIRECT(J$60&"!J10:J29"),$B80,INDIRECT(J$60&"!L10:L29")) -> 0 | ... N80: =SUMIF(INDIRECT(N$60&"!J10:J29"),$B80,INDIRECT(N$60&"!L10:L29")) -> 0
B81: Total Expenses | C81: =SUM(C61:C80) -> 0 | D81: =SUM(D61:D80) -> 0 | E81: =SUM(E61:E80) -> 0 | F81: =SUM(F61:F80) -> 0 | G81: =SUM(G61:G80) -> 0 | H81: =SUM(H61:H80) -> 0 | I81: =SUM(I61:I80) -> 0 | J81: =SUM(J61:J80) -> 0 | ... N81: =SUM(N61:N80) -> 0
B83: Expenses
B84: Name | C84: JAN | D84: FEB | E84: MAR | F84: APR | G84: MAY | H84: JUN | I84: JUL | J84: AUG | K84: SEP | L84: OCT | M84: NOV | N84: DEC
B85: Mortgage | C85: =SUMIF(INDIRECT(C$84&"!N10:N29"),$B85,INDIRECT(C$84&"!P10:P29")) -> 0 | D85: =SUMIF(INDIRECT(D$84&"!N10:N29"),$B85,INDIRECT(D$84&"!P10:P29")) -> 0 | E85: =SUMIF(INDIRECT(E$84&"!N10:N29"),$B85,INDIRECT(E$84&"!P10:P29")) -> 0 | F85: =SUMIF(INDIRECT(F$84&"!N10:N29"),$B85,INDIRECT(F$84&"!P10:P29")) -> 0 | G85: =SUMIF(INDIRECT(G$84&"!N10:N29"),$B85,INDIRECT(G$84&"!P10:P29")) -> 0 | H85: =SUMIF(INDIRECT(H$84&"!N10:N29"),$B85,INDIRECT(H$84&"!P10:P29")) -> 0 | I85: =SUMIF(INDIRECT(I$84&"!N10:N29"),$B85,INDIRECT(I$84&"!P10:P29")) -> 0 | J85: =SUMIF(INDIRECT(J$84&"!N10:N29"),$B85,INDIRECT(J$84&"!P10:P29")) -> 900 | ... N85: =SUMIF(INDIRECT(N$84&"!N10:N29"),$B85,INDIRECT(N$84&"!P10:P29")) -> 0
B86: Student Loan | C86: =SUMIF(INDIRECT(C$84&"!N10:N29"),$B86,INDIRECT(C$84&"!P10:P29")) -> 0 | D86: =SUMIF(INDIRECT(D$84&"!N10:N29"),$B86,INDIRECT(D$84&"!P10:P29")) -> 0 | E86: =SUMIF(INDIRECT(E$84&"!N10:N29"),$B86,INDIRECT(E$84&"!P10:P29")) -> 0 | F86: =SUMIF(INDIRECT(F$84&"!N10:N29"),$B86,INDIRECT(F$84&"!P10:P29")) -> 0 | G86: =SUMIF(INDIRECT(G$84&"!N10:N29"),$B86,INDIRECT(G$84&"!P10:P29")) -> 0 | H86: =SUMIF(INDIRECT(H$84&"!N10:N29"),$B86,INDIRECT(H$84&"!P10:P29")) -> 0 | I86: =SUMIF(INDIRECT(I$84&"!N10:N29"),$B86,INDIRECT(I$84&"!P10:P29")) -> 0 | J86: =SUMIF(INDIRECT(J$84&"!N10:N29"),$B86,INDIRECT(J$84&"!P10:P29")) -> 400 | ... N86: =SUMIF(INDIRECT(N$84&"!N10:N29"),$B86,INDIRECT(N$84&"!P10:P29")) -> 0
B87: Credit Card | C87: =SUMIF(INDIRECT(C$84&"!N10:N29"),$B87,INDIRECT(C$84&"!P10:P29")) -> 0 | D87: =SUMIF(INDIRECT(D$84&"!N10:N29"),$B87,INDIRECT(D$84&"!P10:P29")) -> 0 | E87: =SUMIF(INDIRECT(E$84&"!N10:N29"),$B87,INDIRECT(E$84&"!P10:P29")) -> 0 | F87: =SUMIF(INDIRECT(F$84&"!N10:N29"),$B87,INDIRECT(F$84&"!P10:P29")) -> 0 | G87: =SUMIF(INDIRECT(G$84&"!N10:N29"),$B87,INDIRECT(G$84&"!P10:P29")) -> 0 | H87: =SUMIF(INDIRECT(H$84&"!N10:N29"),$B87,INDIRECT(H$84&"!P10:P29")) -> 0 | I87: =SUMIF(INDIRECT(I$84&"!N10:N29"),$B87,INDIRECT(I$84&"!P10:P29")) -> 0 | J87: =SUMIF(INDIRECT(J$84&"!N10:N29"),$B87,INDIRECT(J$84&"!P10:P29")) -> 400 | ... N87: =SUMIF(INDIRECT(N$84&"!N10:N29"),$B87,INDIRECT(N$84&"!P10:P29")) -> 0
C88: =SUMIF(INDIRECT(C$84&"!N10:N29"),$B88,INDIRECT(C$84&"!P10:P29")) -> 0 | D88: =SUMIF(INDIRECT(D$84&"!N10:N29"),$B88,INDIRECT(D$84&"!P10:P29")) -> 0 | E88: =SUMIF(INDIRECT(E$84&"!N10:N29"),$B88,INDIRECT(E$84&"!P10:P29")) -> 0 | F88: =SUMIF(INDIRECT(F$84&"!N10:N29"),$B88,INDIRECT(F$84&"!P10:P29")) -> 0 | G88: =SUMIF(INDIRECT(G$84&"!N10:N29"),$B88,INDIRECT(G$84&"!P10:P29")) -> 0 | H88: =SUMIF(INDIRECT(H$84&"!N10:N29"),$B88,INDIRECT(H$84&"!P10:P29")) -> 0 | I88: =SUMIF(INDIRECT(I$84&"!N10:N29"),$B88,INDIRECT(I$84&"!P10:P29")) -> 0 | J88: =SUMIF(INDIRECT(J$84&"!N10:N29"),$B88,INDIRECT(J$84&"!P10:P29")) -> 0 | ... N88: =SUMIF(INDIRECT(N$84&"!N10:N29"),$B88,INDIRECT(N$84&"!P10:P29")) -> 0
C89: =SUMIF(INDIRECT(C$84&"!N10:N29"),$B89,INDIRECT(C$84&"!P10:P29")) -> 0 | D89: =SUMIF(INDIRECT(D$84&"!N10:N29"),$B89,INDIRECT(D$84&"!P10:P29")) -> 0 | E89: =SUMIF(INDIRECT(E$84&"!N10:N29"),$B89,INDIRECT(E$84&"!P10:P29")) -> 0 | F89: =SUMIF(INDIRECT(F$84&"!N10:N29"),$B89,INDIRECT(F$84&"!P10:P29")) -> 0 | G89: =SUMIF(INDIRECT(G$84&"!N10:N29"),$B89,INDIRECT(G$84&"!P10:P29")) -> 0 | H89: =SUMIF(INDIRECT(H$84&"!N10:N29"),$B89,INDIRECT(H$84&"!P10:P29")) -> 0 | I89: =SUMIF(INDIRECT(I$84&"!N10:N29"),$B89,INDIRECT(I$84&"!P10:P29")) -> 0 | J89: =SUMIF(INDIRECT(J$84&"!N10:N29"),$B89,INDIRECT(J$84&"!P10:P29")) -> 0 | ... N89: =SUMIF(INDIRECT(N$84&"!N10:N29"),$B89,INDIRECT(N$84&"!P10:P29")) -> 0
C90: =SUMIF(INDIRECT(C$84&"!N10:N29"),$B90,INDIRECT(C$84&"!P10:P29")) -> 0 | D90: =SUMIF(INDIRECT(D$84&"!N10:N29"),$B90,INDIRECT(D$84&"!P10:P29")) -> 0 | E90: =SUMIF(INDIRECT(E$84&"!N10:N29"),$B90,INDIRECT(E$84&"!P10:P29")) -> 0 | F90: =SUMIF(INDIRECT(F$84&"!N10:N29"),$B90,INDIRECT(F$84&"!P10:P29")) -> 0 | G90: =SUMIF(INDIRECT(G$84&"!N10:N29"),$B90,INDIRECT(G$84&"!P10:P29")) -> 0 | H90: =SUMIF(INDIRECT(H$84&"!N10:N29"),$B90,INDIRECT(H$84&"!P10:P29")) -> 0 | I90: =SUMIF(INDIRECT(I$84&"!N10:N29"),$B90,INDIRECT(I$84&"!P10:P29")) -> 0 | J90: =SUMIF(INDIRECT(J$84&"!N10:N29"),$B90,INDIRECT(J$84&"!P10:P29")) -> 0 | ... N90: =SUMIF(INDIRECT(N$84&"!N10:N29"),$B90,INDIRECT(N$84&"!P10:P29")) -> 0
C91: =SUMIF(INDIRECT(C$84&"!N10:N29"),$B91,INDIRECT(C$84&"!P10:P29")) -> 0 | D91: =SUMIF(INDIRECT(D$84&"!N10:N29"),$B91,INDIRECT(D$84&"!P10:P29")) -> 0 | E91: =SUMIF(INDIRECT(E$84&"!N10:N29"),$B91,INDIRECT(E$84&"!P10:P29")) -> 0 | F91: =SUMIF(INDIRECT(F$84&"!N10:N29"),$B91,INDIRECT(F$84&"!P10:P29")) -> 0 | G91: =SUMIF(INDIRECT(G$84&"!N10:N29"),$B91,INDIRECT(G$84&"!P10:P29")) -> 0 | H91: =SUMIF(INDIRECT(H$84&"!N10:N29"),$B91,INDIRECT(H$84&"!P10:P29")) -> 0 | I91: =SUMIF(INDIRECT(I$84&"!N10:N29"),$B91,INDIRECT(I$84&"!P10:P29")) -> 0 | J91: =SUMIF(INDIRECT(J$84&"!N10:N29"),$B91,INDIRECT(J$84&"!P10:P29")) -> 0 | ... N91: =SUMIF(INDIRECT(N$84&"!N10:N29"),$B91,INDIRECT(N$84&"!P10:P29")) -> 0
C92: =SUMIF(INDIRECT(C$84&"!N10:N29"),$B92,INDIRECT(C$84&"!P10:P29")) -> 0 | D92: =SUMIF(INDIRECT(D$84&"!N10:N29"),$B92,INDIRECT(D$84&"!P10:P29")) -> 0 | E92: =SUMIF(INDIRECT(E$84&"!N10:N29"),$B92,INDIRECT(E$84&"!P10:P29")) -> 0 | F92: =SUMIF(INDIRECT(F$84&"!N10:N29"),$B92,INDIRECT(F$84&"!P10:P29")) -> 0 | G92: =SUMIF(INDIRECT(G$84&"!N10:N29"),$B92,INDIRECT(G$84&"!P10:P29")) -> 0 | H92: =SUMIF(INDIRECT(H$84&"!N10:N29"),$B92,INDIRECT(H$84&"!P10:P29")) -> 0 | I92: =SUMIF(INDIRECT(I$84&"!N10:N29"),$B92,INDIRECT(I$84&"!P10:P29")) -> 0 | J92: =SUMIF(INDIRECT(J$84&"!N10:N29"),$B92,INDIRECT(J$84&"!P10:P29")) -> 0 | ... N92: =SUMIF(INDIRECT(N$84&"!N10:N29"),$B92,INDIRECT(N$84&"!P10:P29")) -> 0
C93: =SUMIF(INDIRECT(C$84&"!N10:N29"),$B93,INDIRECT(C$84&"!P10:P29")) -> 0 | D93: =SUMIF(INDIRECT(D$84&"!N10:N29"),$B93,INDIRECT(D$84&"!P10:P29")) -> 0 | E93: =SUMIF(INDIRECT(E$84&"!N10:N29"),$B93,INDIRECT(E$84&"!P10:P29")) -> 0 | F93: =SUMIF(INDIRECT(F$84&"!N10:N29"),$B93,INDIRECT(F$84&"!P10:P29")) -> 0 | G93: =SUMIF(INDIRECT(G$84&"!N10:N29"),$B93,INDIRECT(G$84&"!P10:P29")) -> 0 | H93: =SUMIF(INDIRECT(H$84&"!N10:N29"),$B93,INDIRECT(H$84&"!P10:P29")) -> 0 | I93: =SUMIF(INDIRECT(I$84&"!N10:N29"),$B93,INDIRECT(I$84&"!P10:P29")) -> 0 | J93: =SUMIF(INDIRECT(J$84&"!N10:N29"),$B93,INDIRECT(J$84&"!P10:P29")) -> 0 | ... N93: =SUMIF(INDIRECT(N$84&"!N10:N29"),$B93,INDIRECT(N$84&"!P10:P29")) -> 0
C94: =SUMIF(INDIRECT(C$84&"!N10:N29"),$B94,INDIRECT(C$84&"!P10:P29")) -> 0 | D94: =SUMIF(INDIRECT(D$84&"!N10:N29"),$B94,INDIRECT(D$84&"!P10:P29")) -> 0 | E94: =SUMIF(INDIRECT(E$84&"!N10:N29"),$B94,INDIRECT(E$84&"!P10:P29")) -> 0 | F94: =SUMIF(INDIRECT(F$84&"!N10:N29"),$B94,INDIRECT(F$84&"!P10:P29")) -> 0 | G94: =SUMIF(INDIRECT(G$84&"!N10:N29"),$B94,INDIRECT(G$84&"!P10:P29")) -> 0 | H94: =SUMIF(INDIRECT(H$84&"!N10:N29"),$B94,INDIRECT(H$84&"!P10:P29")) -> 0 | I94: =SUMIF(INDIRECT(I$84&"!N10:N29"),$B94,INDIRECT(I$84&"!P10:P29")) -> 0 | J94: =SUMIF(INDIRECT(J$84&"!N10:N29"),$B94,INDIRECT(J$84&"!P10:P29")) -> 0 | ... N94: =SUMIF(INDIRECT(N$84&"!N10:N29"),$B94,INDIRECT(N$84&"!P10:P29")) -> 0
C95: =SUMIF(INDIRECT(C$84&"!N10:N29"),$B95,INDIRECT(C$84&"!P10:P29")) -> 0 | D95: =SUMIF(INDIRECT(D$84&"!N10:N29"),$B95,INDIRECT(D$84&"!P10:P29")) -> 0 | E95: =SUMIF(INDIRECT(E$84&"!N10:N29"),$B95,INDIRECT(E$84&"!P10:P29")) -> 0 | F95: =SUMIF(INDIRECT(F$84&"!N10:N29"),$B95,INDIRECT(F$84&"!P10:P29")) -> 0 | G95: =SUMIF(INDIRECT(G$84&"!N10:N29"),$B95,INDIRECT(G$84&"!P10:P29")) -> 0 | H95: =SUMIF(INDIRECT(H$84&"!N10:N29"),$B95,INDIRECT(H$84&"!P10:P29")) -> 0 | I95: =SUMIF(INDIRECT(I$84&"!N10:N29"),$B95,INDIRECT(I$84&"!P10:P29")) -> 0 | J95: =SUMIF(INDIRECT(J$84&"!N10:N29"),$B95,INDIRECT(J$84&"!P10:P29")) -> 0 | ... N95: =SUMIF(INDIRECT(N$84&"!N10:N29"),$B95,INDIRECT(N$84&"!P10:P29")) -> 0
C96: =SUMIF(INDIRECT(C$84&"!N10:N29"),$B96,INDIRECT(C$84&"!P10:P29")) -> 0 | D96: =SUMIF(INDIRECT(D$84&"!N10:N29"),$B96,INDIRECT(D$84&"!P10:P29")) -> 0 | E96: =SUMIF(INDIRECT(E$84&"!N10:N29"),$B96,INDIRECT(E$84&"!P10:P29")) -> 0 | F96: =SUMIF(INDIRECT(F$84&"!N10:N29"),$B96,INDIRECT(F$84&"!P10:P29")) -> 0 | G96: =SUMIF(INDIRECT(G$84&"!N10:N29"),$B96,INDIRECT(G$84&"!P10:P29")) -> 0 | H96: =SUMIF(INDIRECT(H$84&"!N10:N29"),$B96,INDIRECT(H$84&"!P10:P29")) -> 0 | I96: =SUMIF(INDIRECT(I$84&"!N10:N29"),$B96,INDIRECT(I$84&"!P10:P29")) -> 0 | J96: =SUMIF(INDIRECT(J$84&"!N10:N29"),$B96,INDIRECT(J$84&"!P10:P29")) -> 0 | ... N96: =SUMIF(INDIRECT(N$84&"!N10:N29"),$B96,INDIRECT(N$84&"!P10:P29")) -> 0
C97: =SUMIF(INDIRECT(C$84&"!N10:N29"),$B97,INDIRECT(C$84&"!P10:P29")) -> 0 | D97: =SUMIF(INDIRECT(D$84&"!N10:N29"),$B97,INDIRECT(D$84&"!P10:P29")) -> 0 | E97: =SUMIF(INDIRECT(E$84&"!N10:N29"),$B97,INDIRECT(E$84&"!P10:P29")) -> 0 | F97: =SUMIF(INDIRECT(F$84&"!N10:N29"),$B97,INDIRECT(F$84&"!P10:P29")) -> 0 | G97: =SUMIF(INDIRECT(G$84&"!N10:N29"),$B97,INDIRECT(G$84&"!P10:P29")) -> 0 | H97: =SUMIF(INDIRECT(H$84&"!N10:N29"),$B97,INDIRECT(H$84&"!P10:P29")) -> 0 | I97: =SUMIF(INDIRECT(I$84&"!N10:N29"),$B97,INDIRECT(I$84&"!P10:P29")) -> 0 | J97: =SUMIF(INDIRECT(J$84&"!N10:N29"),$B97,INDIRECT(J$84&"!P10:P29")) -> 0 | ... N97: =SUMIF(INDIRECT(N$84&"!N10:N29"),$B97,INDIRECT(N$84&"!P10:P29")) -> 0
C98: =SUMIF(INDIRECT(C$84&"!N10:N29"),$B98,INDIRECT(C$84&"!P10:P29")) -> 0 | D98: =SUMIF(INDIRECT(D$84&"!N10:N29"),$B98,INDIRECT(D$84&"!P10:P29")) -> 0 | E98: =SUMIF(INDIRECT(E$84&"!N10:N29"),$B98,INDIRECT(E$84&"!P10:P29")) -> 0 | F98: =SUMIF(INDIRECT(F$84&"!N10:N29"),$B98,INDIRECT(F$84&"!P10:P29")) -> 0 | G98: =SUMIF(INDIRECT(G$84&"!N10:N29"),$B98,INDIRECT(G$84&"!P10:P29")) -> 0 | H98: =SUMIF(INDIRECT(H$84&"!N10:N29"),$B98,INDIRECT(H$84&"!P10:P29")) -> 0 | I98: =SUMIF(INDIRECT(I$84&"!N10:N29"),$B98,INDIRECT(I$84&"!P10:P29")) -> 0 | J98: =SUMIF(INDIRECT(J$84&"!N10:N29"),$B98,INDIRECT(J$84&"!P10:P29")) -> 0 | ... N98: =SUMIF(INDIRECT(N$84&"!N10:N29"),$B98,INDIRECT(N$84&"!P10:P29")) -> 0
C99: =SUMIF(INDIRECT(C$84&"!N10:N29"),$B99,INDIRECT(C$84&"!P10:P29")) -> 0 | D99: =SUMIF(INDIRECT(D$84&"!N10:N29"),$B99,INDIRECT(D$84&"!P10:P29")) -> 0 | E99: =SUMIF(INDIRECT(E$84&"!N10:N29"),$B99,INDIRECT(E$84&"!P10:P29")) -> 0 | F99: =SUMIF(INDIRECT(F$84&"!N10:N29"),$B99,INDIRECT(F$84&"!P10:P29")) -> 0 | G99: =SUMIF(INDIRECT(G$84&"!N10:N29"),$B99,INDIRECT(G$84&"!P10:P29")) -> 0 | H99: =SUMIF(INDIRECT(H$84&"!N10:N29"),$B99,INDIRECT(H$84&"!P10:P29")) -> 0 | I99: =SUMIF(INDIRECT(I$84&"!N10:N29"),$B99,INDIRECT(I$84&"!P10:P29")) -> 0 | J99: =SUMIF(INDIRECT(J$84&"!N10:N29"),$B99,INDIRECT(J$84&"!P10:P29")) -> 0 | ... N99: =SUMIF(INDIRECT(N$84&"!N10:N29"),$B99,INDIRECT(N$84&"!P10:P29")) -> 0
... C104: =SUMIF(INDIRECT(C$84&"!N10:N29"),$B104,INDIRECT(C$84&"!P10:P29")) -> 0 | D104: =SUMIF(INDIRECT(D$84&"!N10:N29"),$B104,INDIRECT(D$84&"!P10:P29")) -> 0 | E104: =SUMIF(INDIRECT(E$84&"!N10:N29"),$B104,INDIRECT(E$84&"!P10:P29")) -> 0 | F104: =SUMIF(INDIRECT(F$84&"!N10:N29"),$B104,INDIRECT(F$84&"!P10:P29")) -> 0 | G104: =SUMIF(INDIRECT(G$84&"!N10:N29"),$B104,INDIRECT(G$84&"!P10:P29")) -> 0 | H104: =SUMIF(INDIRECT(H$84&"!N10:N29"),$B104,INDIRECT(H$84&"!P10:P29")) -> 0 | I104: =SUMIF(INDIRECT(I$84&"!N10:N29"),$B104,INDIRECT(I$84&"!P10:P29")) -> 0 | J104: =SUMIF(INDIRECT(J$84&"!N10:N29"),$B104,INDIRECT(J$84&"!P10:P29")) -> 0 | ... N104: =SUMIF(INDIRECT(N$84&"!N10:N29"),$B104,INDIRECT(N$84&"!P10:P29")) -> 0
B105: Total Expenses | C105: =SUM(C85:C104) -> 0 | D105: =SUM(D85:D104) -> 0 | E105: =SUM(E85:E104) -> 0 | F105: =SUM(F85:F104) -> 0 | G105: =SUM(G85:G104) -> 0 | H105: =SUM(H85:H104) -> 0 | I105: =SUM(I85:I104) -> 0 | J105: =SUM(J85:J104) -> 1700 | ... N105: =SUM(N85:N104) -> 0

Sheet Jan
B2: January | F2: Left to Spend | J2: Total Expenses | N2: Remaining Budget
F3: =D18-J3 -> 19000 | J3: =D30+H30+L30+P30 -> 0 | N3: =D18-C30-G30-K30-O30 -> 19000
B5: Income | F5: Balance Overview | J5: Budget (Left) vs Actual (Right) | N5: Spending Overview
B8: Income | F8: Bills | J8: Expenses | N8: Debt
B9: Name | C9: Payday | D9: Amount | F9: Name | G9: Budget | H9: Actual | J9: Name | K9: Budget | L9: Actual | N9: Name | O9: Budget | P9: Actual
B10: =Apr!B10 -> Burs | C10: =Apr!C10 -> 45748 | D10: =Apr!D10 -> 14000 | F10: Electricity | J10: Groceries | N10: Mortgage
B11: =Apr!B11 -> Maaş | C11: =Apr!C11 -> 45769 | D11: =Apr!D11 -> 5000 | F11: Water | J11: Dining Out | N11: Student Loan
F12: Gas | J12: Fuel | N12: Credit Card
F13: Internet | J13: Shopping
F14: Phone Plan | J14: Beauty
F15: Gym Membership | J15: Entertainment
F16: Car Insurance | J16: Travel
F17: Health Insurance | J17: Gifts
B18: Total | D18: =SUM(D10:D17) -> 19000 | J18: Health
J19: Pets
B20: Savings | J20: Custom Expense 1
B21: Name | C21: Budget | D21: Actual | J21: Custom Expense 2
B22: Emergency Fund
B23: Investment Portfolio
B24: Vacation Fund
B25: New Vehicle
B26: Home Improvement
B30: Total | C30: =SUM(C22:C29) -> 0 | D30: =SUM(D22:D29) -> 0 | F30: Total | G30: =SUM(G10:G29) -> 0 | H30: =SUM(H10:H29) -> 0 | J30: Total | K30: =SUM(K10:K29) -> 0 | L30: =SUM(L10:L29) -> 0 | N30: Total | O30: =SUM(O10:O29) -> 0 | P30: =SUM(P10:P29) -> 0

Sheet Feb
B2: February | F2: Left to Spend | J2: Total Expenses | N2: Remaining Budget
F3: =D18-J3 -> 19000 | J3: =D30+H30+L30+P30 -> 0 | N3: =D18-C30-G30-K30-O30 -> 19000
B5: Income | F5: Balance Overview | J5: Budget (Left) vs Actual (Right) | N5: Spending Overview
B8: Income | F8: Bills | J8: Expenses | N8: Debt
B9: Name | C9: Payday | D9: Amount | F9: Name | G9: Budget | H9: Actual | J9: Name | K9: Budget | L9: Actual | N9: Name | O9: Budget | P9: Actual
B10: =Apr!B10 -> Burs | C10: =Apr!C10 -> 45748 | D10: =Apr!D10 -> 14000 | F10: Electricity | J10: Groceries | N10: Mortgage
B11: =Apr!B11 -> Maaş | C11: =Apr!C11 -> 45769 | D11: =Apr!D11 -> 5000 | F11: Water | J11: Dining Out | N11: Student Loan
F12: Gas | J12: Fuel | N12: Credit Card
F13: Internet | J13: Shopping
F14: Phone Plan | J14: Beauty
F15: Gym Membership | J15: Entertainment
F16: Car Insurance | J16: Travel
F17: Health Insurance | J17: Gifts
B18: Total | D18: =SUM(D10:D17) -> 19000 | J18: Health
A19: 30 | J19: Pets
B20: Savings | J20: Custom Expense 1
B21: Name | C21: Budget | D21: Actual | J21: Custom Expense 2
B22: Emergency Fund
B23: Investment Portfolio
B24: Vacation Fund
B25: New Vehicle
B26: Home Improvement
B30: Total | C30: =SUM(C22:C29) -> 0 | D30: =SUM(D22:D29) -> 0 | F30: Total | G30: =SUM(G10:G29) -> 0 | H30: =SUM(H10:H29) -> 0 | J30: Total | K30: =SUM(K10:K29) -> 0 | L30: =SUM(L10:L29) -> 0 | N30: Total | O30: =SUM(O10:O29) -> 0 | P30: =SUM(P10:P29) -> 0

Sheet Mar
B2: March | F2: Left to Spend | J2: Total Expenses | N2: Remaining Budget
F3: =D18-J3 -> -15900 | J3: =D30+H30+L30+P30 -> 34900 | N3: =D18-C30-G30-K30-O30 -> -3500
B5: Income | F5: Balance Overview | J5: Budget (Left) vs Actual (Right) | N5: Spending Overview
B8: Income | F8: Bills | J8: Expenses | N8: Debt
B9: Name | C9: Payday | D9: Amount | F9: Name | G9: Budget | H9: Actual | J9: Name | K9: Budget | L9: Actual | N9: Name | O9: Budget | P9: Actual
B10: =Apr!B10 -> Burs | C10: =Apr!C10 -> 45748 | D10: =Apr!D10 -> 14000 | F10: Electricity | J10: Groceries | N10: Mortgage
B11: =Apr!B11 -> Maaş | C11: =Apr!C11 -> 45769 | D11: =Apr!D11 -> 5000 | F11: Water | J11: Dining Out | N11: Student Loan
F12: Gas | J12: Fuel | N12: Credit Card
F13: Internet | J13: Shopping
F14: Phone Plan | J14: Beauty
F15: Gym Membership | J15: Entertainment
F16: Car Insurance | J16: Travel
F17: Health Insurance | J17: Gifts
B18: Total | D18: =SUM(D10:D17) -> 19000 | J18: Health
J19: Pets
B20: Savings | J20: Custom Expense 1
B21: Name | C21: Budget | D21: Actual | J21: Custom Expense 2
B22: YBL Para fonu | C22: 15000 | D22: 15000
B23: Altın | C23: 7500 | D23: 19900
B30: Total | C30: =SUM(C22:C29) -> 22500 | D30: =SUM(D22:D29) -> 34900 | F30: Total | G30: =SUM(G10:G29) -> 0 | H30: =SUM(H10:H29) -> 0 | J30: Total | K30: =SUM(K10:K29) -> 0 | L30: =SUM(L10:L29) -> 0 | N30: Total | O30: =SUM(O10:O29) -> 0 | P30: =SUM(P10:P29) -> 0

Sheet Apr
B2: April | F2: Left to Spend | J2: Total Expenses | N2: Remaining Budget
F3: =D18-J3 -> 19000 | J3: =D30+H30+L30+P30 -> 0 | N3: =D18-C30-G30-K30-O30 -> 16000
B5: Income | F5: Balance Overview | J5: Budget (Left) vs Actual (Right) | N5: Spending Overview
B8: Income | F8: Bills | J8: Expenses | N8: Debt
B9: Name | C9: Payday | D9: Amount | F9: Name | G9: Budget | H9: Actual | J9: Name | K9: Budget | L9: Actual | N9: Name | O9: Budget | P9: Actual
B10: Burs | C10: =IF(ROW()=9, DATE(2025, 4, 1), DATE(2025, 4, 1)) -> 45748 | D10: 14000 | F10: Electricity | J10: Yiyecek | N10: ahmetcan borç | O10: 3000
B11: Maaş | C11: =IF(ROW()=10, DATE(2025, 4, 1), DATE(2025, 4, 22)) -> 45769 | D11: 5000 | F11: Water | J11: Dining Out
F12: Gas | J12: Fuel
F13: Internet | J13: Shopping
F14: Phone Plan | J14: Beauty
F15: Gym Membership | J15: Entertainment
F16: Car Insurance | J16: Travel
J17: Gifts
B18: Total | D18: =SUM(D10:D17) -> 19000 | J18: Health
J19: Pets
B20: Savings | J20: Custom Expense 1
B21: Name | C21: Budget | D21: Actual | J21: Custom Expense 2
B22: Emergency Fund
B23: Investment Portfolio
B24: Vacation Fund
B25: New Vehicle
B26: Home Improvement
B30: Total | C30: =SUM(C22:C29) -> 0 | D30: =SUM(D22:D29) -> 0 | F30: Total | G30: =SUM(G10:G29) -> 0 | H30: =SUM(H10:H29) -> 0 | J30: Total | K30: =SUM(K10:K29) -> 0 | L30: =SUM(L10:L29) -> 0 | N30: Total | O30: =SUM(O10:O29) -> 3000 | P30: =SUM(P10:P29) -> 0

Sheet May
B2: May | F2: Left to Spend | J2: Total Expenses | N2: Remaining Budget
F3: =D18-J3 -> 19000 | J3: =D30+H30+L30+P30 -> 0 | N3: =D18-C30-G30-K30-O30 -> 19000
B5: Income | F5: Balance Overview | J5: Budget (Left) vs Actual (Right) | N5: Spending Overview
B8: Income | F8: Bills | J8: Expenses | N8: Debt
B9: Name | C9: Payday | D9: Amount | F9: Name | G9: Budget | H9: Actual | J9: Name | K9: Budget | L9: Actual | N9: Name | O9: Budget | P9: Actual
B10: =Apr!B10 -> Burs | C10: =Apr!C10 -> 45748 | D10: =Apr!D10 -> 14000 | F10: Electricity | J10: Groceries | N10: Mortgage
B11: =Apr!B11 -> Maaş | C11: =Apr!C11 -> 45769 | D11: =Apr!D11 -> 5000 | F11: Water | J11: Dining Out | N11: Student Loan
F12: Gas | J12: Fuel | N12: Credit Card
F13: Internet | J13: Shopping
F14: Phone Plan | J14: Beauty
F15: Gym Membership | J15: Entertainment
F16: Car Insurance | J16: Travel
F17: Health Insurance | J17: Gifts
B18: Total | D18: =SUM(D10:D17) -> 19000 | J18: Health
J19: Pets
B20: Savings | J20: Custom Expense 1
B21: Name | C21: Budget | D21: Actual | J21: Custom Expense 2
B22: Emergency Fund
B23: Investment Portfolio
B24: Vacation Fund
B25: New Vehicle
B26: Home Improvement
B30: Total | C30: =SUM(C22:C29) -> 0 | D30: =SUM(D22:D29) -> 0 | F30: Total | G30: =SUM(G10:G29) -> 0 | H30: =SUM(H10:H29) -> 0 | J30: Total | K30: =SUM(K10:K29) -> 0 | L30: =SUM(L10:L29) -> 0 | N30: Total | O30: =SUM(O10:O29) -> 0 | P30: =SUM(P10:P29) -> 0

Sheet Jun
B2: June | F2: Left to Spend | J2: Total Expenses | N2: Remaining Budget
F3: =D18-J3 -> 19000 | J3: =D30+H30+L30+P30 -> 0 | N3: =D18-C30-G30-K30-O30 -> 19000
B5: Income | F5: Balance Overview | J5: Budget (Left) vs Actual (Right) | N5: Spending Overview
B8: Income | F8: Bills | J8: Expenses | N8: Debt
B9: Name | C9: Payday | D9: Amount | F9: Name | G9: Budget | H9: Actual | J9: Name | K9: Budget | L9: Actual | N9: Name | O9: Budget | P9: Actual
B10: =Apr!B10 -> Burs | C10: =Apr!C10 -> 45748 | D10: =Apr!D10 -> 14000 | F10: Electricity | J10: Groceries | N10: Mortgage
B11: =Apr!B11 -> Maaş | C11: =Apr!C11 -> 45769 | D11: =Apr!D11 -> 5000 | F11: Water | J11: Dining Out | N11: Student Loan
F12: Gas | J12: Fuel | N12: Credit Card
F13: Internet | J13: Shopping
F14: Phone Plan | J14: Beauty
F15: Gym Membership | J15: Entertainment
F16: Car Insurance | J16: Travel
F17: Health Insurance | J17: Gifts
B18: Total | D18: =SUM(D10:D17) -> 19000 | J18: Health
J19: Pets
B20: Savings | J20: Custom Expense 1
B21: Name | C21: Budget | D21: Actual | J21: Custom Expense 2
B22: Emergency Fund
B23: Investment Portfolio
B24: Vacation Fund
B25: New Vehicle
B26: Home Improvement
B30: Total | C30: =SUM(C22:C29) -> 0 | D30: =SUM(D22:D29) -> 0 | F30: Total | G30: =SUM(G10:G29) -> 0 | H30: =SUM(H10:H29) -> 0 | J30: Total | K30: =SUM(K10:K29) -> 0 | L30: =SUM(L10:L29) -> 0 | N30: Total | O30: =SUM(O10:O29) -> 0 | P30: =SUM(P10:P29) -> 0

Sheet Jul
B2: July | F2: Left to Spend | J2: Total Expenses | N2: Remaining Budget
F3: =D18-J3 -> 19000 | J3: =D30+H30+L30+P30 -> 0 | N3: =D18-C30-G30-K30-O30 -> 19000
B5: Income | F5: Balance Overview | J5: Budget (Left) vs Actual (Right) | N5: Spending Overview
B8: Income | F8: Bills | J8: Expenses | N8: Debt
B9: Name | C9: Payday | D9: Amount | F9: Name | G9: Budget | H9: Actual | J9: Name | K9: Budget | L9: Actual | N9: Name | O9: Budget | P9: Actual
B10: =Apr!B10 -> Burs | C10: =Apr!C10 -> 45748 | D10: =Apr!D10 -> 14000 | F10: Electricity | J10: Groceries | N10: Mortgage
B11: =Apr!B11 -> Maaş | C11: =Apr!C11 -> 45769 | D11: =Apr!D11 -> 5000 | F11: Water | J11: Dining Out | N11: Student Loan
F12: Gas | J12: Fuel | N12: Credit Card
F13: Internet | J13: Shopping
F14: Phone Plan | J14: Beauty
F15: Gym Membership | J15: Entertainment
F16: Car Insurance | J16: Travel
F17: Health Insurance | J17: Gifts
B18: Total | D18: =SUM(D10:D17) -> 19000 | J18: Health
J19: Pets
B20: Savings | J20: Custom Expense 1
B21: Name | C21: Budget | D21: Actual | J21: Custom Expense 2
B22: Emergency Fund
B23: Investment Portfolio
B24: Vacation Fund
B25: New Vehicle
B26: Home Improvement
B30: Total | C30: =SUM(C22:C29) -> 0 | D30: =SUM(D22:D29) -> 0 | F30: Total | G30: =SUM(G10:G29) -> 0 | H30: =SUM(H10:H29) -> 0 | J30: Total | K30: =SUM(K10:K29) -> 0 | L30: =SUM(L10:L29) -> 0 | N30: Total | O30: =SUM(O10:O29) -> 0 | P30: =SUM(P10:P29) -> 0

Sheet Aug
B2: August | F2: Left to Spend | J2: Total Expenses | N2: Remaining Budget
F3: =D18-J3 -> 15465 | J3: =D30+H30+L30+P30 -> 3535 | N3: =D18-C30-G30-K30-O30 -> 15950
B5: Income | F5: Balance Overview | J5: Budget (Left) vs Actual (Right) | N5: Spending Overview
B8: Income | F8: Bills | J8: Expenses | N8: Debt
B9: Name | C9: Payday | D9: Amount | F9: Name | G9: Budget | H9: Actual | J9: Name | K9: Budget | L9: Actual | N9: Name | O9: Budget | P9: Actual
B10: =Apr!B10 -> Burs | C10: =Apr!C10 -> 45748 | D10: =Apr!D10 -> 14000 | F10: Electricity | J10: Groceries | N10: Mortgage | O10: 900 | P10: 900
B11: =Apr!B11 -> Maaş | C11: =Apr!C11 -> 45769 | D11: =Apr!D11 -> 5000 | F11: Water | J11: Dining Out | N11: Student Loan | O11: 400 | P11: 400
F12: Gas | J12: Fuel | N12: Credit Card | O12: 200 | P12: 400
F13: Internet | J13: Shopping
F14: Phone Plan | J14: Beauty
F15: Gym Membership | J15: Entertainment
F16: Car Insurance | J16: Travel
F17: Health Insurance | J17: Gifts
B18: Total | D18: =SUM(D10:D17) -> 19000 | J18: Health
J19: Pets
B20: Savings | J20: Custom Expense 1
B21: Name | C21: Budget | D21: Actual | J21: Custom Expense 2
B22: Emergency Fund | C22: 300 | D22: 325
B23: Investment Portfolio | C23: 500 | D23: 550
B24: Vacation Fund | C24: 200 | D24: 210
B25: New Vehicle | C25: 400 | D25: 550
B26: Home Improvement | C26: 150 | D26: 200
B30: Total | C30: =SUM(C22:C29) -> 1550 | D30: =SUM(D22:D29) -> 1835 | F30: Total | G30: =SUM(G10:G29) -> 0 | H30: =SUM(H10:H29) -> 0 | J30: Total | K30: =SUM(K10:K29) -> 0 | L30: =SUM(L10:L29) -> 0 | N30: Total | O30: =SUM(O10:O29) -> 1500 | P30: =SUM(P10:P29) -> 1700

Sheet Sep
B2: September | F2: Left to Spend | J2: Total Expenses | N2: Remaining Budget
F3: =D18-J3 -> 19000 | J3: =D30+H30+L30+P30 -> 0 | N3: =D18-C30-G30-K30-O30 -> 19000
B5: Income | F5: Balance Overview | J5: Budget (Left) vs Actual (Right) | N5: Spending Overview
B8: Income | F8: Bills | J8: Expenses | N8: Debt
B9: Name | C9: Payday | D9: Amount | F9: Name | G9: Budget | H9: Actual | J9: Name | K9: Budget | L9: Actual | N9: Name | O9: Budget | P9: Actual
B10: =Apr!B10 -> Burs | C10: =Apr!C10 -> 45748 | D10: =Apr!D10 -> 14000 | F10: Electricity | J10: Groceries | N10: Mortgage
B11: =Apr!B11 -> Maaş | C11: =Apr!C11 -> 45769 | D11: =Apr!D11 -> 5000 | F11: Water | J11: Dining Out | N11: Student Loan
F12: Gas | J12: Fuel | N12: Credit Card
F13: Internet | J13: Shopping
F14: Phone Plan | J14: Beauty
F15: Gym Membership | J15: Entertainment
F16: Car Insurance | J16: Travel
F17: Health Insurance | J17: Gifts
B18: Total | D18: =SUM(D10:D17) -> 19000 | J18: Health
J19: Pets
B20: Savings | J20: Custom Expense 1
B21: Name | C21: Budget | D21: Actual | J21: Custom Expense 2
B22: Emergency Fund
B23: Investment Portfolio
B24: Vacation Fund
B25: New Vehicle
B26: Home Improvement
B30: Total | C30: =SUM(C22:C29) -> 0 | D30: =SUM(D22:D29) -> 0 | F30: Total | G30: =SUM(G10:G29) -> 0 | H30: =SUM(H10:H29) -> 0 | J30: Total | K30: =SUM(K10:K29) -> 0 | L30: =SUM(L10:L29) -> 0 | N30: Total | O30: =SUM(O10:O29) -> 0 | P30: =SUM(P10:P29) -> 0

Sheet Oct
B2: October | F2: Left to Spend | J2: Total Expenses | N2: Remaining Budget
F3: =D18-J3 -> 19000 | J3: =D30+H30+L30+P30 -> 0 | N3: =D18-C30-G30-K30-O30 -> 19000
B5: Income | F5: Balance Overview | J5: Budget (Left) vs Actual (Right) | N5: Spending Overview
B8: Income | F8: Bills | J8: Expenses | N8: Debt
B9: Name | C9: Payday | D9: Amount | F9: Name | G9: Budget | H9: Actual | J9: Name | K9: Budget | L9: Actual | N9: Name | O9: Budget | P9: Actual
B10: =Apr!B10 -> Burs | C10: =Apr!C10 -> 45748 | D10: =Apr!D10 -> 14000 | F10: Electricity | J10: Groceries | N10: Mortgage
B11: =Apr!B11 -> Maaş | C11: =Apr!C11 -> 45769 | D11: =Apr!D11 -> 5000 | F11: Water | J11: Dining Out | N11: Student Loan
F12: Gas | J12: Fuel | N12: Credit Card
F13: Internet | J13: Shopping
F14: Phone Plan | J14: Beauty
F15: Gym Membership | J15: Entertainment
F16: Car Insurance | J16: Travel
F17: Health Insurance | J17: Gifts
B18: Total | D18: =SUM(D10:D17) -> 19000 | J18: Health
J19: Pets
B20: Savings | J20: Custom Expense 1
B21: Name | C21: Budget | D21: Actual | J21: Custom Expense 2
B22: Emergency Fund
B23: Investment Portfolio
B24: Vacation Fund
B25: New Vehicle
B26: Home Improvement
B30: Total | C30: =SUM(C22:C29) -> 0 | D30: =SUM(D22:D29) -> 0 | F30: Total | G30: =SUM(G10:G29) -> 0 | H30: =SUM(H10:H29) -> 0 | J30: Total | K30: =SUM(K10:K29) -> 0 | L30: =SUM(L10:L29) -> 0 | N30: Total | O30: =SUM(O10:O29) -> 0 | P30: =SUM(P10:P29) -> 0

Sheet Nov
B2: November | F2: Left to Spend | J2: Total Expenses | N2: Remaining Budget
F3: =D18-J3 -> 19000 | J3: =D30+H30+L30+P30 -> 0 | N3: =D18-C30-G30-K30-O30 -> 19000
B5: Income | F5: Balance Overview | J5: Budget (Left) vs Actual (Right) | N5: Spending Overview
B8: Income | F8: Bills | J8: Expenses | N8: Debt
B9: Name | C9: Payday | D9: Amount | F9: Name | G9: Budget | H9: Actual | J9: Name | K9: Budget | L9: Actual | N9: Name | O9: Budget | P9: Actual
B10: =Apr!B10 -> Burs | C10: =Apr!C10 -> 45748 | D10: =Apr!D10 -> 14000 | F10: Electricity | J10: Groceries | N10: Mortgage
B11: =Apr!B11 -> Maaş | C11: =Apr!C11 -> 45769 | D11: =Apr!D11 -> 5000 | F11: Water | J11: Dining Out | N11: Student Loan
F12: Gas | J12: Fuel | N12: Credit Card
F13: Internet | J13: Shopping
F14: Phone Plan | J14: Beauty
F15: Gym Membership | J15: Entertainment
F16: Car Insurance | J16: Travel
F17: Health Insurance | J17: Gifts
B18: Total | D18: =SUM(D10:D17) -> 19000 | J18: Health
J19: Pets
B20: Savings | J20: Custom Expense 1
B21: Name | C21: Budget | D21: Actual | J21: Custom Expense 2
B22: Emergency Fund
B23: Investment Portfolio
B24: Vacation Fund
B25: New Vehicle
B26: Home Improvement
B30: Total | C30: =SUM(C22:C29) -> 0 | D30: =SUM(D22:D29) -> 0 | F30: Total | G30: =SUM(G10:G29) -> 0 | H30: =SUM(H10:H29) -> 0 | J30: Total | K30: =SUM(K10:K29) -> 0 | L30: =SUM(L10:L29) -> 0 | N30: Total | O30: =SUM(O10:O29) -> 0 | P30: =SUM(P10:P29) -> 0

Sheet Dec
B2: December | F2: Left to Spend | J2: Total Expenses | N2: Remaining Budget
F3: =D18-J3 -> 19000 | J3: =D30+H30+L30+P30 -> 0 | N3: =D18-C30-G30-K30-O30 -> 19000
B5: Income | F5: Balance Overview | J5: Budget (Left) vs Actual (Right) | N5: Spending Overview
B8: Income | F8: Bills | J8: Expenses | N8: Debt
B9: Name | C9: Payday | D9: Amount | F9: Name | G9: Budget | H9: Actual | J9: Name | K9: Budget | L9: Actual | N9: Name | O9: Budget | P9: Actual
B10: =Apr!B10 -> Burs | C10: =Apr!C10 -> 45748 | D10: =Apr!D10 -> 14000 | F10: Electricity | J10: Groceries | N10: Mortgage
B11: =Apr!B11 -> Maaş | C11: =Apr!C11 -> 45769 | D11: =Apr!D11 -> 5000 | F11: Water | J11: Dining Out | N11: Student Loan
F12: Gas | J12: Fuel | N12: Credit Card
F13: Internet | J13: Shopping
F14: Phone Plan | J14: Beauty
F15: Gym Membership | J15: Entertainment
F16: Car Insurance | J16: Travel
F17: Health Insurance | J17: Gifts
B18: Total | D18: =SUM(D10:D17) -> 19000 | J18: Health
J19: Pets
B20: Savings | J20: Custom Expense 1
B21: Name | C21: Budget | D21: Actual | J21: Custom Expense 2
B22: Emergency Fund
B23: Investment Portfolio
B24: Vacation Fund
B25: New Vehicle
B26: Home Improvement
B30: Total | C30: =SUM(C22:C29) -> 0 | D30: =SUM(D22:D29) -> 0 | F30: Total | G30: =SUM(G10:G29) -> 0 | H30: =SUM(H10:H29) -> 0 | J30: Total | K30: =SUM(K10:K29) -> 0 | L30: =SUM(L10:L29) -> 0 | N30: Total | O30: =SUM(O10:O29) -> 0 | P30: =SUM(P10:P29) -> 0

Sheet Chart Data for Each Month
B2: Budget (Left) vs Actual (Right) Jan | F2: Budget (Left) vs Actual (Right) Feb | J2: Budget (Left) vs Actual (Right) Mar | N2: Budget (Left) vs Actual (Right) Apr | R2: Budget (Left) vs Actual (Right) May | V2: Budget (Left) vs Actual (Right) Jun
B3: Name | C3: Budget | D3: Actual | F3: Name | G3: Budget | H3: Actual | J3: Name | K3: Budget | L3: Actual | N3: Name | O3: Budget | P3: Actual | R3: Name | S3: Budget | T3: Actual | V3: Name | W3: Budget | X3: Actual
B4: Savings | C4: =Jan!C30 -> 0 | D4: =Jan!D30 -> 0 | F4: Savings | G4: =Feb!C30 -> 0 | H4: =Feb!D30 -> 0 | J4: Savings | K4: =Mar!C30 -> 22500 | L4: =Mar!D30 -> 34900 | N4: Savings | O4: =Apr!$C30 -> 0 | P4: =Apr!$D30 -> 0 | R4: Savings | S4: =May!$C30 -> 0 | T4: =May!$D30 -> 0 | V4: Savings | W4: =Jun!$C30 -> 0 | X4: =Jun!$D30 -> 0
B5: Bills | C5: =Jan!G30 -> 0 | D5: =Jan!H30 -> 0 | F5: Bills | G5: =Feb!G30 -> 0 | H5: =Feb!H30 -> 0 | J5: Bills | K5: =Mar!G30 -> 0 | L5: =Mar!H30 -> 0 | N5: Bills | O5: =Apr!$G30 -> 0 | P5: =Apr!$H30 -> 0 | R5: Bills | S5: =May!$G30 -> 0 | T5: =May!$H30 -> 0 | V5: Bills | W5: =Jun!$G30 -> 0 | X5: =Jun!$H30 -> 0
B6: Expenses | C6: =Jan!K30 -> 0 | D6: =Jan!L30 -> 0 | F6: Expenses | G6: =Feb!K30 -> 0 | H6: =Feb!L30 -> 0 | J6: Expenses | K6: =Mar!K30 -> 0 | L6: =Mar!L30 -> 0 | N6: Expenses | O6: =Apr!$K30 -> 0 | P6: =Apr!$L30 -> 0 | R6: Expenses | S6: =May!$K30 -> 0 | T6: =May!$L30 -> 0 | V6: Expenses | W6: =Jun!$K30 -> 0 | X6: =Jun!$L30 -> 0
B7: Debt | C7: =Jan!O30 -> 0 | D7: =Jan!P30 -> 0 | F7: Debt | G7: =Feb!O30 -> 0 | H7: =Feb!P30 -> 0 | J7: Debt | K7: =Mar!O30 -> 0 | L7: =Mar!P30 -> 0 | N7: Debt | O7: =Apr!$O30 -> 3000 | P7: =Apr!$P30 -> 0 | R7: Debt | S7: =May!$O30 -> 0 | T7: =May!$P30 -> 0 | V7: Debt | W7: =Jun!$O30 -> 0 | X7: =Jun!$P30 -> 0
B8: Spending Overview Jan | F8: Spending Overview Feb | J8: Spending Overview Mar | N8: Spending Overview Apr | R8: Spending Overview May | V8: Spending Overview Jun
B9: Name | C9: Amount | F9: Name | G9: Amount | J9: Name | K9: Amount | N9: Name | O9: Amount | R9: Name | S9: Amount | V9: Name | W9: Amount
B10: Savings | C10: =Jan!D30 -> 0 | F10: Savings | G10: =Feb!D30 -> 0 | J10: Savings | K10: =Mar!D30 -> 34900 | N10: Savings | O10: =Apr!D30 -> 0 | R10: Savings | S10: =May!$D30 -> 0 | V10: Savings | W10: =Jun!$D30 -> 0
B11: Bills | C11: =Jan!H30 -> 0 | F11: Bills | G11: =Feb!H30 -> 0 | J11: Bills | K11: =Mar!H30 -> 0 | N11: Bills | O11: =Apr!H30 -> 0 | R11: Bills | S11: =May!$H30 -> 0 | V11: Bills | W11: =Jun!$H30 -> 0
B12: Expenses | C12: =Jan!L30 -> 0 | F12: Expenses | G12: =Feb!L30 -> 0 | J12: Expenses | K12: =Mar!L30 -> 0 | N12: Expenses | O12: =Apr!L30 -> 0 | R12: Expenses | S12: =May!$L30 -> 0 | V12: Expenses | W12: =Jun!$L30 -> 0
B13: Debt | C13: =Jan!P30 -> 0 | F13: Debt | G13: =Feb!P30 -> 0 | J13: Debt | K13: =Mar!P30 -> 0 | N13: Debt | O13: =Apr!P30 -> 0 | R13: Debt | S13: =May!$P30 -> 0 | V13: Debt | W13: =Jun!$P30 -> 0
B15: Budget (Left) vs Actual (Right) Jul | F15: Budget (Left) vs Actual (Right) Aug | J15: Budget (Left) vs Actual (Right) Sep | N15: Budget (Left) vs Actual (Right) Oct | R15: Budget (Left) vs Actual (Right) Nov | V15: Budget (Left) vs Actual (Right) Dec
B16: Name | C16: Budget | D16: Actual | F16: Name | G16: Budget | H16: Actual | J16: Name | K16: Budget | L16: Actual | N16: Name | O16: Budget | P16: Actual | R16: Name | S16: Budget | T16: Actual | V16: Name | W16: Budget | X16: Actual
B17: Savings | C17: =Jul!$C30 -> 0 | D17: =Jul!$D30 -> 0 | F17: Savings | G17: =Aug!$C30 -> 1550 | H17: =Aug!$D30 -> 1835 | J17: Savings | K17: =Sep!$C30 -> 0 | L17: =Sep!$D30 -> 0 | N17: Savings | O17: =Oct!$C30 -> 0 | P17: =Oct!$D30 -> 0 | R17: Savings | S17: =Nov!$C30 -> 0 | T17: =Nov!$D30 -> 0 | V17: Savings | W17: =Dec!$C30 -> 0 | X17: =Dec!$D30 -> 0
B18: Bills | C18: =Jul!$G30 -> 0 | D18: =Jul!$H30 -> 0 | F18: Bills | G18: =Aug!$G30 -> 0 | H18: =Aug!$H30 -> 0 | J18: Bills | K18: =Sep!$G30 -> 0 | L18: =Sep!$H30 -> 0 | N18: Bills | O18: =Oct!$G30 -> 0 | P18: =Oct!$H30 -> 0 | R18: Bills | S18: =Nov!$G30 -> 0 | T18: =Nov!$H30 -> 0 | V18: Bills | W18: =Dec!$G30 -> 0 | X18: =Dec!$H30 -> 0
B19: Expenses | C19: =Jul!$K30 -> 0 | D19: =Jul!$L30 -> 0 | F19: Expenses | G19: =Aug!$K30 -> 0 | H19: =Aug!$L30 -> 0 | J19: Expenses | K19: =Sep!$K30 -> 0 | L19: =Sep!$L30 -> 0 | N19: Expenses | O19: =Oct!$K30 -> 0 | P19: =Oct!$L30 -> 0 | R19: Expenses | S19: =Nov!$K30 -> 0 | T19: =Nov!$L30 -> 0 | V19: Expenses | W19: =Dec!$K30 -> 0 | X19: =Dec!$L30 -> 0
B20: Debt | C20: =Jul!$O30 -> 0 | D20: =Jul!$P30 -> 0 | F20: Debt | G20: =Aug!$O30 -> 1500 | H20: =Aug!$P30 -> 1700 | J20: Debt | K20: =Sep!$O30 -> 0 | L20: =Sep!$P30 -> 0 | N20: Debt | O20: =Oct!$O30 -> 0 | P20: =Oct!$P30 -> 0 | R20: Debt | S20: =Nov!$O30 -> 0 | T20: =Nov!$P30 -> 0 | V20: Debt | W20: =Dec!$O30 -> 0 | X20: =Dec!$P30 -> 0
B21: Spending Overview Jul | F21: Spending Overview Aug | J21: Spending Overview Sep | N21: Spending Overview Oct | R21: Spending Overview Nov | V21: Spending Overview Dec
B22: Name | C22: Amount | F22: Name | G22: Amount | J22: Name | K22: Amount | N22: Name | O22: Amount | R22: Name | S22: Amount | V22: Name | W22: Amount
B23: Savings | C23: =Jul!$D30 -> 0 | F23: Savings | G23: =Aug!$D30 -> 1835 | J23: Savings | K23: =Sep!$D30 -> 0 | N23: Savings | O23: =Oct!$D30 -> 0 | R23: Savings | S23: =Nov!$D30 -> 0 | V23: Savings | W23: =Dec!$D30 -> 0
B24: Bills | C24: =Jul!$H30 -> 0 | F24: Bills | G24: =Aug!$H30 -> 0 | J24: Bills | K24: =Sep!$H30 -> 0 | N24: Bills | O24: =Oct!$H30 -> 0 | R24: Bills | S24: =Nov!$H30 -> 0 | V24: Bills | W24: =Dec!$H30 -> 0
B25: Expenses | C25: =Jul!$L30 -> 0 | F25: Expenses | G25: =Aug!$L30 -> 0 | J25: Expenses | K25: =Sep!$L30 -> 0 | N25: Expenses | O25: =Oct!$L30 -> 0 | R25: Expenses | S25: =Nov!$L30 -> 0 | V25: Expenses | W25: =Dec!$L30 -> 0
B26: Debt | C26: =Jul!$P30 -> 0 | F26: Debt | G26: =Aug!$P30 -> 1700 | J26: Debt | K26: =Sep!$P30 -> 0 | N26: Debt | O26: =Oct!$P30 -> 0 | R26: Debt | S26: =Nov!$P30 -> 0 | V26: Debt | W26: =Dec!$P30 -> 0
